{"v":"4.8.0","meta":{"g":"LottieFiles AE 3.4.3","a":"","k":"","d":"","tc":""},"fr":29.9700012207031,"ip":0,"op":240.0000097754,"w":1125,"h":2436,"nm":"레이어 1/0404_MatchingLoadingView","ddd":0,"assets":[{"id":"image_0","w":748,"h":748,"u":"","p":"image_0.png","e":1},{"id":"image_1","w":747,"h":747,"u":"","p":"image_1.png","e":1}],"layers":[{"ddd":0,"ind":1,"ty":2,"nm":"보름달","refId":"image_0","sr":1,"ks":{"o":{"a":1,"k":[{"i":{"x":[0.667],"y":[1]},"o":{"x":[0.333],"y":[0]},"t":0,"s":[0]},{"i":{"x":[0.667],"y":[1]},"o":{"x":[0.333],"y":[0]},"t":107,"s":[0]},{"t":180.00000733155,"s":[70]}],"ix":11},"r":{"a":0,"k":0,"ix":10},"p":{"a":0,"k":[562,909.5,0],"ix":2},"a":{"a":0,"k":[374,374,0],"ix":1},"s":{"a":1,"k":[{"i":{"x":[0.667,0.667,0.667],"y":[1,1,1]},"o":{"x":[0.333,0.333,0.333],"y":[0,0,0]},"t":140,"s":[40,40,100]},{"t":190.000007738859,"s":[50,50,100]}],"ix":6}},"ao":0,"ip":0,"op":239.00000973467,"st":0,"bm":0},{"ddd":0,"ind":2,"ty":4,"nm":"상대조명","sr":1,"ks":{"o":{"a":1,"k":[{"i":{"x":[0.667],"y":[1]},"o":{"x":[0.333],"y":[0]},"t":0,"s":[40]},{"i":{"x":[0.667],"y":[1]},"o":{"x":[0.333],"y":[0]},"t":45,"s":[70]},{"i":{"x":[0.667],"y":[1]},"o":{"x":[0.333],"y":[0]},"t":90,"s":[40]},{"i":{"x":[0.667],"y":[1]},"o":{"x":[0.167],"y":[0]},"t":152,"s":[100]},{"t":190.000007738859,"s":[0]}],"ix":11},"r":{"a":1,"k":[{"i":{"x":[0.667],"y":[1]},"o":{"x":[0.333],"y":[0]},"t":0,"s":[-20]},{"i":{"x":[0.667],"y":[1]},"o":{"x":[0.333],"y":[0]},"t":45,"s":[-40]},{"i":{"x":[0.667],"y":[1]},"o":{"x":[0.333],"y":[0]},"t":90,"s":[-20]},{"t":152.000006191087,"s":[-30]}],"ix":10},"p":{"a":0,"k":[1222.219,2046,0],"ix":2},"a":{"a":0,"k":[394.5,1898,0],"ix":1},"s":{"a":1,"k":[{"i":{"x":[0.667,0.667,0.667],"y":[1,1,1]},"o":{"x":[0.333,0.333,0.333],"y":[0,0,0]},"t":0,"s":[70,70,100]},{"i":{"x":[0.667,0.667,0.667],"y":[1,1,1]},"o":{"x":[0.333,0.333,0.333],"y":[0,0,0]},"t":45,"s":[120,120,100]},{"i":{"x":[0.667,0.667,0.667],"y":[1,1,1]},"o":{"x":[0.333,0.333,0.333],"y":[0,0,0]},"t":90,"s":[140,140,100]},{"t":152.000006191087,"s":[80,80,100]}],"ix":6}},"ao":0,"shapes":[{"ty":"gr","it":[{"ind":0,"ty":"sh","ix":1,"ks":{"a":0,"k":{"i":[[66.667,-541],[66.667,541],[-110.457,0],[0,-110.457]],"o":[[-66.667,-541],[0,-110.457],[110.457,0],[-66.667,541]],"v":[[0,911.5],[-200,-711.5],[0,-911.5],[200,-711.5]],"c":true},"ix":2},"nm":"패스 1","mn":"ADBE Vector Shape - Group","hd":false},{"ty":"mm","mm":4,"nm":"패스 병합 1","mn":"ADBE Vector Filter - Merge","hd":false},{"ty":"gf","o":{"a":0,"k":100,"ix":10},"r":1,"bm":0,"g":{"p":2,"k":{"a":0,"k":[0,1,1,1,1,0,0,0],"ix":9}},"s":{"a":0,"k":[-16.064,1439.542],"ix":5},"e":{"a":0,"k":[2.566,-1720.322],"ix":6},"t":1,"nm":"그라디언트 칠 1","mn":"ADBE Vector Graphic - G-Fill","hd":false},{"ty":"tr","p":{"a":0,"k":[389.719,970.156],"ix":2},"a":{"a":0,"k":[0,0],"ix":1},"s":{"a":0,"k":[100,100],"ix":3},"r":{"a":0,"k":0,"ix":6},"o":{"a":0,"k":100,"ix":7},"sk":{"a":0,"k":0,"ix":4},"sa":{"a":0,"k":0,"ix":5},"nm":"변형"}],"nm":"그룹 1","np":3,"cix":2,"bm":0,"ix":1,"mn":"ADBE Vector Group","hd":false}],"ip":0,"op":239.00000973467,"st":0,"bm":0},{"ddd":0,"ind":3,"ty":2,"nm":"반달","refId":"image_1","sr":1,"ks":{"o":{"a":0,"k":100,"ix":11},"r":{"a":0,"k":0,"ix":10},"p":{"a":0,"k":[562,910,0],"ix":2},"a":{"a":0,"k":[373.5,373.5,0],"ix":1},"s":{"a":1,"k":[{"i":{"x":[0.667,0.667,0.667],"y":[1,1,1]},"o":{"x":[0.333,0.333,0.333],"y":[0,0,0]},"t":140,"s":[40,40,100]},{"t":190.000007738859,"s":[50,50,100]}],"ix":6}},"ao":0,"ip":0,"op":239.00000973467,"st":0,"bm":0},{"ddd":0,"ind":4,"ty":4,"nm":"내조명","sr":1,"ks":{"o":{"a":1,"k":[{"i":{"x":[0.667],"y":[1]},"o":{"x":[0.333],"y":[0]},"t":0,"s":[70]},{"i":{"x":[0.667],"y":[1]},"o":{"x":[0.333],"y":[0]},"t":39,"s":[40]},{"i":{"x":[0.667],"y":[1]},"o":{"x":[0.333],"y":[0]},"t":75,"s":[70]},{"i":{"x":[0.667],"y":[1]},"o":{"x":[0.333],"y":[0]},"t":113,"s":[40]},{"i":{"x":[0.833],"y":[1]},"o":{"x":[0.333],"y":[0]},"t":149,"s":[70]},{"t":190.000007738859,"s":[0]}],"ix":11},"r":{"a":0,"k":30,"ix":10},"p":{"a":0,"k":[-91.781,2048,0],"ix":2},"a":{"a":0,"k":[394.5,1898,0],"ix":1},"s":{"a":0,"k":[80,80,100],"ix":6}},"ao":0,"shapes":[{"ty":"gr","it":[{"ind":0,"ty":"sh","ix":1,"ks":{"a":0,"k":{"i":[[66.667,-541],[66.667,541],[-110.457,0],[0,-110.457]],"o":[[-66.667,-541],[0,-110.457],[110.457,0],[-66.667,541]],"v":[[0,911.5],[-200,-711.5],[0,-911.5],[200,-711.5]],"c":true},"ix":2},"nm":"패스 1","mn":"ADBE Vector Shape - Group","hd":false},{"ty":"mm","mm":4,"nm":"패스 병합 1","mn":"ADBE Vector Filter - Merge","hd":false},{"ty":"gf","o":{"a":0,"k":100,"ix":10},"r":1,"bm":0,"g":{"p":2,"k":{"a":0,"k":[0,1,1,1,1,0,0,0],"ix":9}},"s":{"a":0,"k":[-16.064,1439.542],"ix":5},"e":{"a":0,"k":[2.566,-1720.322],"ix":6},"t":1,"nm":"그라디언트 칠 1","mn":"ADBE Vector Graphic - G-Fill","hd":false},{"ty":"tr","p":{"a":0,"k":[389.719,970.156],"ix":2},"a":{"a":0,"k":[0,0],"ix":1},"s":{"a":0,"k":[100,100],"ix":3},"r":{"a":0,"k":0,"ix":6},"o":{"a":0,"k":100,"ix":7},"sk":{"a":0,"k":0,"ix":4},"sa":{"a":0,"k":0,"ix":5},"nm":"변형"}],"nm":"그룹 1","np":3,"cix":2,"bm":0,"ix":1,"mn":"ADBE Vector Group","hd":false}],"ip":0,"op":239.00000973467,"st":0,"bm":0},{"ddd":0,"ind":5,"ty":4,"nm":"산 3","sr":1,"ks":{"o":{"a":0,"k":100,"ix":11},"r":{"a":0,"k":0,"ix":10},"p":{"a":0,"k":[1326.5,742,0],"ix":2},"a":{"a":0,"k":[562.5,1250,0],"ix":1},"s":{"a":0,"k":[100,100,100],"ix":6}},"ao":0,"shapes":[{"ty":"gr","it":[{"ind":0,"ty":"sh","ix":1,"ks":{"a":0,"k":{"i":[[0,0],[-135.934,-75.65],[0,0],[173.73,0],[0,0],[-152.155,83.846]],"o":[[78.296,-49.65],[0,0],[152.157,83.846],[0,0],[-173.73,0],[0,0]],"v":[[-426.064,-244.355],[-101.834,-240.355],[288.518,-19.078],[207.402,296.182],[-697.3,296.182],[-902.415,66.922]],"c":true},"ix":2},"nm":"패스 1","mn":"ADBE Vector Shape - Group","hd":false},{"ty":"mm","mm":4,"nm":"패스 병합 1","mn":"ADBE Vector Filter - Merge","hd":false},{"ty":"gf","o":{"a":0,"k":100,"ix":10},"r":1,"bm":0,"g":{"p":2,"k":{"a":0,"k":[0,1,1,1,1,0,0,0],"ix":9}},"s":{"a":0,"k":[-238.687,-296.219],"ix":5},"e":{"a":0,"k":[-249.937,1124.547],"ix":6},"t":1,"nm":"그라디언트 칠 1","mn":"ADBE Vector Graphic - G-Fill","hd":false},{"ty":"tr","p":{"a":0,"k":[129.768,2704.005],"ix":2},"a":{"a":0,"k":[0,0],"ix":1},"s":{"a":0,"k":[100,100],"ix":3},"r":{"a":0,"k":0,"ix":6},"o":{"a":0,"k":100,"ix":7},"sk":{"a":0,"k":0,"ix":4},"sa":{"a":0,"k":0,"ix":5},"nm":"변형"}],"nm":"그룹 3","np":3,"cix":2,"bm":0,"ix":1,"mn":"ADBE Vector Group","hd":false}],"ip":0,"op":239.00000973467,"st":0,"bm":0},{"ddd":0,"ind":6,"ty":4,"nm":"산 2","sr":1,"ks":{"o":{"a":0,"k":100,"ix":11},"r":{"a":0,"k":0,"ix":10},"p":{"a":0,"k":[1768.5,714,0],"ix":2},"a":{"a":0,"k":[562.5,1250,0],"ix":1},"s":{"a":0,"k":[100,100,100],"ix":6}},"ao":0,"shapes":[{"ty":"gr","it":[{"ind":0,"ty":"sh","ix":1,"ks":{"a":0,"k":{"i":[[0,0],[-135.934,-75.65],[0,0],[173.73,0],[0,0],[-152.155,83.846]],"o":[[78.296,-49.65],[0,0],[152.157,83.846],[0,0],[-173.73,0],[0,0]],"v":[[-426.064,-244.355],[-101.834,-240.355],[288.518,-19.078],[207.402,296.182],[-697.3,296.182],[-902.415,66.922]],"c":true},"ix":2},"nm":"패스 1","mn":"ADBE Vector Shape - Group","hd":false},{"ty":"mm","mm":4,"nm":"패스 병합 1","mn":"ADBE Vector Filter - Merge","hd":false},{"ty":"gf","o":{"a":0,"k":100,"ix":10},"r":1,"bm":0,"g":{"p":2,"k":{"a":0,"k":[0,1,1,1,1,0,0,0],"ix":9}},"s":{"a":0,"k":[-238.687,-296.219],"ix":5},"e":{"a":0,"k":[-249.937,1124.547],"ix":6},"t":1,"nm":"그라디언트 칠 1","mn":"ADBE Vector Graphic - G-Fill","hd":false},{"ty":"tr","p":{"a":0,"k":[129.768,2704.005],"ix":2},"a":{"a":0,"k":[0,0],"ix":1},"s":{"a":0,"k":[100,100],"ix":3},"r":{"a":0,"k":0,"ix":6},"o":{"a":0,"k":100,"ix":7},"sk":{"a":0,"k":0,"ix":4},"sa":{"a":0,"k":0,"ix":5},"nm":"변형"}],"nm":"그룹 3","np":3,"cix":2,"bm":0,"ix":1,"mn":"ADBE Vector Group","hd":false}],"ip":0,"op":239.00000973467,"st":0,"bm":0},{"ddd":0,"ind":7,"ty":4,"nm":"산","sr":1,"ks":{"o":{"a":0,"k":100,"ix":11},"r":{"a":0,"k":0,"ix":10},"p":{"a":0,"k":[944.5,682,0],"ix":2},"a":{"a":0,"k":[562.5,1250,0],"ix":1},"s":{"a":0,"k":[100,100,100],"ix":6}},"ao":0,"shapes":[{"ty":"gr","it":[{"ind":0,"ty":"sh","ix":1,"ks":{"a":0,"k":{"i":[[0,0],[-50.496,-27.827],[0,0],[173.73,0],[0,0],[-152.155,83.846]],"o":[[50.497,-27.827],[0,0],[152.157,83.846],[0,0],[-173.73,0],[0,0]],"v":[[-326.064,-268.355],[-163.834,-268.355],[288.518,-19.078],[207.402,296.182],[-697.3,296.182],[-778.415,-19.078]],"c":true},"ix":2},"nm":"패스 1","mn":"ADBE Vector Shape - Group","hd":false},{"ty":"mm","mm":4,"nm":"패스 병합 1","mn":"ADBE Vector Filter - Merge","hd":false},{"ty":"gf","o":{"a":0,"k":100,"ix":10},"r":1,"bm":0,"g":{"p":2,"k":{"a":0,"k":[0,1,1,1,1,0,0,0],"ix":9}},"s":{"a":0,"k":[-238.687,-296.219],"ix":5},"e":{"a":0,"k":[-249.937,1124.547],"ix":6},"t":1,"nm":"그라디언트 칠 1","mn":"ADBE Vector Graphic - G-Fill","hd":false},{"ty":"tr","p":{"a":0,"k":[129.768,2704.005],"ix":2},"a":{"a":0,"k":[0,0],"ix":1},"s":{"a":0,"k":[100,100],"ix":3},"r":{"a":0,"k":0,"ix":6},"o":{"a":0,"k":100,"ix":7},"sk":{"a":0,"k":0,"ix":4},"sa":{"a":0,"k":0,"ix":5},"nm":"변형"}],"nm":"그룹 3","np":3,"cix":2,"bm":0,"ix":1,"mn":"ADBE Vector Group","hd":false}],"ip":0,"op":239.00000973467,"st":0,"bm":0},{"ddd":0,"ind":8,"ty":4,"nm":"별3","sr":1,"ks":{"o":{"a":1,"k":[{"i":{"x":[0.833],"y":[0.833]},"o":{"x":[0.167],"y":[0.167]},"t":0,"s":[50]},{"i":{"x":[0.833],"y":[0.833]},"o":{"x":[0.167],"y":[0.167]},"t":41,"s":[80]},{"i":{"x":[0.833],"y":[0.833]},"o":{"x":[0.167],"y":[0.167]},"t":77,"s":[50]},{"i":{"x":[0.833],"y":[0.833]},"o":{"x":[0.167],"y":[0.167]},"t":115,"s":[80]},{"i":{"x":[0.833],"y":[0.833]},"o":{"x":[0.167],"y":[0.167]},"t":153,"s":[50]},{"i":{"x":[0.833],"y":[0.833]},"o":{"x":[0.167],"y":[0.167]},"t":194,"s":[80]},{"t":239.00000973467,"s":[50]}],"ix":11},"r":{"a":0,"k":0,"ix":10},"p":{"a":0,"k":[562,1218,0],"ix":2},"a":{"a":0,"k":[562.5,1218,0],"ix":1},"s":{"a":0,"k":[100,100,100],"ix":6}},"ao":0,"shapes":[{"ty":"gr","it":[{"ind":0,"ty":"sh","ix":1,"ks":{"a":0,"k":{"i":[[-0.725,0],[0,-0.725],[0.725,0],[0,0.725]],"o":[[0.725,0],[0,0.725],[-0.725,0],[0,-0.725]],"v":[[0,-1.313],[1.313,0],[0,1.313],[-1.313,0]],"c":true},"ix":2},"nm":"패스 1","mn":"ADBE Vector Shape - Group","hd":false},{"ty":"fl","c":{"a":0,"k":[1,1,1,1],"ix":4},"o":{"a":0,"k":100,"ix":5},"r":1,"bm":0,"nm":"칠 1","mn":"ADBE Vector Graphic - Fill","hd":false},{"ty":"tr","p":{"a":0,"k":[962.067,1863.027],"ix":2},"a":{"a":0,"k":[0,0],"ix":1},"s":{"a":0,"k":[100,100],"ix":3},"r":{"a":0,"k":0,"ix":6},"o":{"a":0,"k":100,"ix":7},"sk":{"a":0,"k":0,"ix":4},"sa":{"a":0,"k":0,"ix":5},"nm":"변형"}],"nm":"그룹 1","np":4,"cix":2,"bm":0,"ix":1,"mn":"ADBE Vector Group","hd":false},{"ty":"gr","it":[{"ind":0,"ty":"sh","ix":1,"ks":{"a":0,"k":{"i":[[-0.725,0],[0,-0.725],[0.725,0],[0,0.725]],"o":[[0.725,0],[0,0.725],[-0.725,0],[0,-0.725]],"v":[[0,-1.313],[1.313,0],[0,1.313],[-1.313,0]],"c":true},"ix":2},"nm":"패스 1","mn":"ADBE Vector Shape - Group","hd":false},{"ty":"fl","c":{"a":0,"k":[1,1,1,1],"ix":4},"o":{"a":0,"k":100,"ix":5},"r":1,"bm":0,"nm":"칠 1","mn":"ADBE Vector Graphic - Fill","hd":false},{"ty":"tr","p":{"a":0,"k":[90.227,1973.32],"ix":2},"a":{"a":0,"k":[0,0],"ix":1},"s":{"a":0,"k":[100,100],"ix":3},"r":{"a":0,"k":0,"ix":6},"o":{"a":0,"k":100,"ix":7},"sk":{"a":0,"k":0,"ix":4},"sa":{"a":0,"k":0,"ix":5},"nm":"변형"}],"nm":"그룹 2","np":4,"cix":2,"bm":0,"ix":2,"mn":"ADBE Vector Group","hd":false},{"ty":"gr","it":[{"ind":0,"ty":"sh","ix":1,"ks":{"a":0,"k":{"i":[[-0.725,0],[0,-0.725],[0.725,0],[0,0.725]],"o":[[0.725,0],[0,0.725],[-0.725,0],[0,-0.725]],"v":[[0,-1.313],[1.313,0],[0,1.313],[-1.313,0]],"c":true},"ix":2},"nm":"패스 1","mn":"ADBE Vector Shape - Group","hd":false},{"ty":"fl","c":{"a":0,"k":[1,1,1,1],"ix":4},"o":{"a":0,"k":100,"ix":5},"r":1,"bm":0,"nm":"칠 1","mn":"ADBE Vector Graphic - Fill","hd":false},{"ty":"tr","p":{"a":0,"k":[145.373,1834.14],"ix":2},"a":{"a":0,"k":[0,0],"ix":1},"s":{"a":0,"k":[100,100],"ix":3},"r":{"a":0,"k":0,"ix":6},"o":{"a":0,"k":100,"ix":7},"sk":{"a":0,"k":0,"ix":4},"sa":{"a":0,"k":0,"ix":5},"nm":"변형"}],"nm":"그룹 3","np":4,"cix":2,"bm":0,"ix":3,"mn":"ADBE Vector Group","hd":false},{"ty":"gr","it":[{"ind":0,"ty":"sh","ix":1,"ks":{"a":0,"k":{"i":[[-0.725,0],[0,-0.725],[0.725,0],[0,0.725]],"o":[[0.725,0],[0,0.725],[-0.725,0],[0,-0.725]],"v":[[0,-1.313],[1.313,0],[0,1.313],[-1.313,0]],"c":true},"ix":2},"nm":"패스 1","mn":"ADBE Vector Shape - Group","hd":false},{"ty":"fl","c":{"a":0,"k":[1,1,1,1],"ix":4},"o":{"a":0,"k":100,"ix":5},"r":1,"bm":0,"nm":"칠 1","mn":"ADBE Vector Graphic - Fill","hd":false},{"ty":"tr","p":{"a":0,"k":[772.993,1645.066],"ix":2},"a":{"a":0,"k":[0,0],"ix":1},"s":{"a":0,"k":[100,100],"ix":3},"r":{"a":0,"k":0,"ix":6},"o":{"a":0,"k":100,"ix":7},"sk":{"a":0,"k":0,"ix":4},"sa":{"a":0,"k":0,"ix":5},"nm":"변형"}],"nm":"그룹 4","np":4,"cix":2,"bm":0,"ix":4,"mn":"ADBE Vector Group","hd":false},{"ty":"gr","it":[{"ind":0,"ty":"sh","ix":1,"ks":{"a":0,"k":{"i":[[-0.725,0],[0,-0.725],[0.725,0],[0,0.725]],"o":[[0.725,0],[0,0.725],[-0.725,0],[0,-0.725]],"v":[[0,-1.313],[1.313,0],[0,1.313],[-1.313,0]],"c":true},"ix":2},"nm":"패스 1","mn":"ADBE Vector Shape - Group","hd":false},{"ty":"fl","c":{"a":0,"k":[1,1,1,1],"ix":4},"o":{"a":0,"k":100,"ix":5},"r":1,"bm":0,"nm":"칠 1","mn":"ADBE Vector Graphic - Fill","hd":false},{"ty":"tr","p":{"a":0,"k":[830.766,1519.017],"ix":2},"a":{"a":0,"k":[0,0],"ix":1},"s":{"a":0,"k":[100,100],"ix":3},"r":{"a":0,"k":0,"ix":6},"o":{"a":0,"k":100,"ix":7},"sk":{"a":0,"k":0,"ix":4},"sa":{"a":0,"k":0,"ix":5},"nm":"변형"}],"nm":"그룹 5","np":4,"cix":2,"bm":0,"ix":5,"mn":"ADBE Vector Group","hd":false},{"ty":"gr","it":[{"ind":0,"ty":"sh","ix":1,"ks":{"a":0,"k":{"i":[[-0.725,0],[0,-0.725],[0.725,0],[0,0.725]],"o":[[0.725,0],[0,0.725],[-0.725,0],[0,-0.725]],"v":[[0,-1.312],[1.313,0.001],[0,1.314],[-1.313,0.001]],"c":true},"ix":2},"nm":"패스 1","mn":"ADBE Vector Shape - Group","hd":false},{"ty":"fl","c":{"a":0,"k":[1,1,1,1],"ix":4},"o":{"a":0,"k":100,"ix":5},"r":1,"bm":0,"nm":"칠 1","mn":"ADBE Vector Graphic - Fill","hd":false},{"ty":"tr","p":{"a":0,"k":[597.05,862.51],"ix":2},"a":{"a":0,"k":[0,0],"ix":1},"s":{"a":0,"k":[100,100],"ix":3},"r":{"a":0,"k":0,"ix":6},"o":{"a":0,"k":100,"ix":7},"sk":{"a":0,"k":0,"ix":4},"sa":{"a":0,"k":0,"ix":5},"nm":"변형"}],"nm":"그룹 6","np":4,"cix":2,"bm":0,"ix":6,"mn":"ADBE Vector Group","hd":false},{"ty":"gr","it":[{"ind":0,"ty":"sh","ix":1,"ks":{"a":0,"k":{"i":[[-0.725,0],[0,-0.725],[0.725,0],[0,0.725]],"o":[[0.725,0],[0,0.725],[-0.725,0],[0,-0.725]],"v":[[0,-1.313],[1.313,0],[0,1.313],[-1.313,0]],"c":true},"ix":2},"nm":"패스 1","mn":"ADBE Vector Shape - Group","hd":false},{"ty":"fl","c":{"a":0,"k":[1,1,1,1],"ix":4},"o":{"a":0,"k":100,"ix":5},"r":1,"bm":0,"nm":"칠 1","mn":"ADBE Vector Graphic - Fill","hd":false},{"ty":"tr","p":{"a":0,"k":[1032.97,442.347],"ix":2},"a":{"a":0,"k":[0,0],"ix":1},"s":{"a":0,"k":[100,100],"ix":3},"r":{"a":0,"k":0,"ix":6},"o":{"a":0,"k":100,"ix":7},"sk":{"a":0,"k":0,"ix":4},"sa":{"a":0,"k":0,"ix":5},"nm":"변형"}],"nm":"그룹 7","np":4,"cix":2,"bm":0,"ix":7,"mn":"ADBE Vector Group","hd":false},{"ty":"gr","it":[{"ind":0,"ty":"sh","ix":1,"ks":{"a":0,"k":{"i":[[-0.725,0],[0,-0.725],[0.725,0],[0,0.725]],"o":[[0.725,0],[0,0.725],[-0.725,0],[0,-0.725]],"v":[[0,-1.313],[1.313,0],[0,1.313],[-1.313,0]],"c":true},"ix":2},"nm":"패스 1","mn":"ADBE Vector Shape - Group","hd":false},{"ty":"fl","c":{"a":0,"k":[1,1,1,1],"ix":4},"o":{"a":0,"k":100,"ix":5},"r":1,"bm":0,"nm":"칠 1","mn":"ADBE Vector Graphic - Fill","hd":false},{"ty":"tr","p":{"a":0,"k":[1030.344,1450.741],"ix":2},"a":{"a":0,"k":[0,0],"ix":1},"s":{"a":0,"k":[100,100],"ix":3},"r":{"a":0,"k":0,"ix":6},"o":{"a":0,"k":100,"ix":7},"sk":{"a":0,"k":0,"ix":4},"sa":{"a":0,"k":0,"ix":5},"nm":"변형"}],"nm":"그룹 8","np":4,"cix":2,"bm":0,"ix":8,"mn":"ADBE Vector Group","hd":false},{"ty":"gr","it":[{"ind":0,"ty":"sh","ix":1,"ks":{"a":0,"k":{"i":[[-0.725,0],[0,-0.725],[0.725,0],[0,0.725]],"o":[[0.725,0],[0,0.725],[-0.725,0],[0,-0.725]],"v":[[0,-1.313],[1.313,0],[0,1.313],[-1.313,0]],"c":true},"ix":2},"nm":"패스 1","mn":"ADBE Vector Shape - Group","hd":false},{"ty":"fl","c":{"a":0,"k":[1,1,1,1],"ix":4},"o":{"a":0,"k":100,"ix":5},"r":1,"bm":0,"nm":"칠 1","mn":"ADBE Vector Graphic - Fill","hd":false},{"ty":"tr","p":{"a":0,"k":[87.601,1125.114],"ix":2},"a":{"a":0,"k":[0,0],"ix":1},"s":{"a":0,"k":[100,100],"ix":3},"r":{"a":0,"k":0,"ix":6},"o":{"a":0,"k":100,"ix":7},"sk":{"a":0,"k":0,"ix":4},"sa":{"a":0,"k":0,"ix":5},"nm":"변형"}],"nm":"그룹 9","np":4,"cix":2,"bm":0,"ix":9,"mn":"ADBE Vector Group","hd":false}],"ip":0,"op":239.00000973467,"st":0,"bm":0},{"ddd":0,"ind":9,"ty":4,"nm":"별2","sr":1,"ks":{"o":{"a":1,"k":[{"i":{"x":[0.833],"y":[0.833]},"o":{"x":[0.167],"y":[0.167]},"t":0,"s":[30]},{"i":{"x":[0.833],"y":[0.833]},"o":{"x":[0.167],"y":[0.167]},"t":41,"s":[80]},{"i":{"x":[0.833],"y":[0.833]},"o":{"x":[0.167],"y":[0.167]},"t":77,"s":[30]},{"i":{"x":[0.833],"y":[0.833]},"o":{"x":[0.167],"y":[0.167]},"t":115,"s":[80]},{"i":{"x":[0.833],"y":[0.833]},"o":{"x":[0.167],"y":[0.167]},"t":149,"s":[30]},{"i":{"x":[0.833],"y":[0.833]},"o":{"x":[0.167],"y":[0.167]},"t":194,"s":[80]},{"t":239.00000973467,"s":[30]}],"ix":11},"r":{"a":0,"k":0,"ix":10},"p":{"a":0,"k":[562,802,0],"ix":2},"a":{"a":0,"k":[562.5,1218,0],"ix":1},"s":{"a":0,"k":[100,100,100],"ix":6}},"ao":0,"shapes":[{"ty":"gr","it":[{"ind":0,"ty":"sh","ix":1,"ks":{"a":0,"k":{"i":[[-2.175,0],[0,-2.175],[2.175,0],[0,2.176]],"o":[[2.175,0],[0,2.176],[-2.175,0],[0,-2.175]],"v":[[0,-3.939],[3.939,0],[0,3.939],[-3.939,0]],"c":true},"ix":2},"nm":"패스 1","mn":"ADBE Vector Shape - Group","hd":false},{"ty":"fl","c":{"a":0,"k":[1,1,1,1],"ix":4},"o":{"a":0,"k":100,"ix":5},"r":1,"bm":0,"nm":"칠 1","mn":"ADBE Vector Graphic - Fill","hd":false},{"ty":"tr","p":{"a":0,"k":[199.207,879.58],"ix":2},"a":{"a":0,"k":[0,0],"ix":1},"s":{"a":0,"k":[100,100],"ix":3},"r":{"a":0,"k":0,"ix":6},"o":{"a":0,"k":100,"ix":7},"sk":{"a":0,"k":0,"ix":4},"sa":{"a":0,"k":0,"ix":5},"nm":"변형"}],"nm":"그룹 1","np":4,"cix":2,"bm":0,"ix":1,"mn":"ADBE Vector Group","hd":false},{"ty":"gr","it":[{"ind":0,"ty":"sh","ix":1,"ks":{"a":0,"k":{"i":[[-2.175,0],[0,-2.175],[2.175,0],[0,2.176]],"o":[[2.175,0],[0,2.176],[-2.175,0],[0,-2.175]],"v":[[0,-3.939],[3.939,0],[0,3.939],[-3.939,0]],"c":true},"ix":2},"nm":"패스 1","mn":"ADBE Vector Shape - Group","hd":false},{"ty":"fl","c":{"a":0,"k":[1,1,1,1],"ix":4},"o":{"a":0,"k":100,"ix":5},"r":1,"bm":0,"nm":"칠 1","mn":"ADBE Vector Graphic - Fill","hd":false},{"ty":"tr","p":{"a":0,"k":[884.599,1147.435],"ix":2},"a":{"a":0,"k":[0,0],"ix":1},"s":{"a":0,"k":[100,100],"ix":3},"r":{"a":0,"k":0,"ix":6},"o":{"a":0,"k":100,"ix":7},"sk":{"a":0,"k":0,"ix":4},"sa":{"a":0,"k":0,"ix":5},"nm":"변형"}],"nm":"그룹 2","np":4,"cix":2,"bm":0,"ix":2,"mn":"ADBE Vector Group","hd":false},{"ty":"gr","it":[{"ind":0,"ty":"sh","ix":1,"ks":{"a":0,"k":{"i":[[-2.175,0],[0,-2.175],[2.175,0],[0,2.176]],"o":[[2.175,0],[0,2.176],[-2.175,0],[0,-2.175]],"v":[[0,-3.938],[3.939,0.001],[0,3.94],[-3.939,0.001]],"c":true},"ix":2},"nm":"패스 1","mn":"ADBE Vector Shape - Group","hd":false},{"ty":"fl","c":{"a":0,"k":[1,1,1,1],"ix":4},"o":{"a":0,"k":100,"ix":5},"r":1,"bm":0,"nm":"칠 1","mn":"ADBE Vector Graphic - Fill","hd":false},{"ty":"tr","p":{"a":0,"k":[354.142,680.002],"ix":2},"a":{"a":0,"k":[0,0],"ix":1},"s":{"a":0,"k":[100,100],"ix":3},"r":{"a":0,"k":0,"ix":6},"o":{"a":0,"k":100,"ix":7},"sk":{"a":0,"k":0,"ix":4},"sa":{"a":0,"k":0,"ix":5},"nm":"변형"}],"nm":"그룹 3","np":4,"cix":2,"bm":0,"ix":3,"mn":"ADBE Vector Group","hd":false},{"ty":"gr","it":[{"ind":0,"ty":"sh","ix":1,"ks":{"a":0,"k":{"i":[[-2.175,0],[0,-2.175],[2.175,0],[0,2.176]],"o":[[2.175,0],[0,2.176],[-2.175,0],[0,-2.175]],"v":[[0,-3.938],[3.939,0.001],[0,3.94],[-3.939,0.001]],"c":true},"ix":2},"nm":"패스 1","mn":"ADBE Vector Shape - Group","hd":false},{"ty":"fl","c":{"a":0,"k":[1,1,1,1],"ix":4},"o":{"a":0,"k":100,"ix":5},"r":1,"bm":0,"nm":"칠 1","mn":"ADBE Vector Graphic - Fill","hd":false},{"ty":"tr","p":{"a":0,"k":[913.486,580.212],"ix":2},"a":{"a":0,"k":[0,0],"ix":1},"s":{"a":0,"k":[100,100],"ix":3},"r":{"a":0,"k":0,"ix":6},"o":{"a":0,"k":100,"ix":7},"sk":{"a":0,"k":0,"ix":4},"sa":{"a":0,"k":0,"ix":5},"nm":"변형"}],"nm":"그룹 4","np":4,"cix":2,"bm":0,"ix":4,"mn":"ADBE Vector Group","hd":false},{"ty":"gr","it":[{"ind":0,"ty":"sh","ix":1,"ks":{"a":0,"k":{"i":[[-1.45,0],[0,-1.45],[1.45,0],[0,1.45]],"o":[[1.45,0],[0,1.45],[-1.45,0],[0,-1.45]],"v":[[0,-2.626],[2.626,0],[0,2.626],[-2.626,0]],"c":true},"ix":2},"nm":"패스 1","mn":"ADBE Vector Shape - Group","hd":false},{"ty":"fl","c":{"a":0,"k":[1,1,1,1],"ix":4},"o":{"a":0,"k":100,"ix":5},"r":1,"bm":0,"nm":"칠 1","mn":"ADBE Vector Graphic - Fill","hd":false},{"ty":"tr","p":{"a":0,"k":[103.357,922.91],"ix":2},"a":{"a":0,"k":[0,0],"ix":1},"s":{"a":0,"k":[100,100],"ix":3},"r":{"a":0,"k":0,"ix":6},"o":{"a":0,"k":100,"ix":7},"sk":{"a":0,"k":0,"ix":4},"sa":{"a":0,"k":0,"ix":5},"nm":"변형"}],"nm":"그룹 5","np":4,"cix":2,"bm":0,"ix":5,"mn":"ADBE Vector Group","hd":false},{"ty":"gr","it":[{"ind":0,"ty":"sh","ix":1,"ks":{"a":0,"k":{"i":[[-1.45,0],[0,-1.45],[1.45,0],[0,1.45]],"o":[[1.45,0],[0,1.45],[-1.45,0],[0,-1.45]],"v":[[0,-2.626],[2.626,0],[0,2.626],[-2.626,0]],"c":true},"ix":2},"nm":"패스 1","mn":"ADBE Vector Shape - Group","hd":false},{"ty":"fl","c":{"a":0,"k":[1,1,1,1],"ix":4},"o":{"a":0,"k":100,"ix":5},"r":1,"bm":0,"nm":"칠 1","mn":"ADBE Vector Graphic - Fill","hd":false},{"ty":"tr","p":{"a":0,"k":[77.097,1587.294],"ix":2},"a":{"a":0,"k":[0,0],"ix":1},"s":{"a":0,"k":[100,100],"ix":3},"r":{"a":0,"k":0,"ix":6},"o":{"a":0,"k":100,"ix":7},"sk":{"a":0,"k":0,"ix":4},"sa":{"a":0,"k":0,"ix":5},"nm":"변형"}],"nm":"그룹 6","np":4,"cix":2,"bm":0,"ix":6,"mn":"ADBE Vector Group","hd":false},{"ty":"gr","it":[{"ind":0,"ty":"sh","ix":1,"ks":{"a":0,"k":{"i":[[-1.45,0],[0,-1.45],[1.45,0],[0,1.45]],"o":[[1.45,0],[0,1.45],[-1.45,0],[0,-1.45]],"v":[[0,-2.626],[2.626,0],[0,2.626],[-2.626,0]],"c":true},"ix":2},"nm":"패스 1","mn":"ADBE Vector Shape - Group","hd":false},{"ty":"fl","c":{"a":0,"k":[1,1,1,1],"ix":4},"o":{"a":0,"k":100,"ix":5},"r":1,"bm":0,"nm":"칠 1","mn":"ADBE Vector Graphic - Fill","hd":false},{"ty":"tr","p":{"a":0,"k":[612.806,1836.766],"ix":2},"a":{"a":0,"k":[0,0],"ix":1},"s":{"a":0,"k":[100,100],"ix":3},"r":{"a":0,"k":0,"ix":6},"o":{"a":0,"k":100,"ix":7},"sk":{"a":0,"k":0,"ix":4},"sa":{"a":0,"k":0,"ix":5},"nm":"변형"}],"nm":"그룹 7","np":4,"cix":2,"bm":0,"ix":7,"mn":"ADBE Vector Group","hd":false},{"ty":"gr","it":[{"ind":0,"ty":"sh","ix":1,"ks":{"a":0,"k":{"i":[[-1.45,0],[0,-1.45],[1.45,0],[0,1.45]],"o":[[1.45,0],[0,1.45],[-1.45,0],[0,-1.45]],"v":[[0.002,-2.627],[2.628,-0.001],[0.002,2.625],[-2.624,-0.001]],"c":true},"ix":2},"nm":"패스 1","mn":"ADBE Vector Shape - Group","hd":false},{"ty":"fl","c":{"a":0,"k":[1,1,1,1],"ix":4},"o":{"a":0,"k":100,"ix":5},"r":1,"bm":0,"nm":"칠 1","mn":"ADBE Vector Graphic - Fill","hd":false},{"ty":"tr","p":{"a":0,"k":[1053.976,1290.555],"ix":2},"a":{"a":0,"k":[0,0],"ix":1},"s":{"a":0,"k":[100,100],"ix":3},"r":{"a":0,"k":0,"ix":6},"o":{"a":0,"k":100,"ix":7},"sk":{"a":0,"k":0,"ix":4},"sa":{"a":0,"k":0,"ix":5},"nm":"변형"}],"nm":"그룹 8","np":4,"cix":2,"bm":0,"ix":8,"mn":"ADBE Vector Group","hd":false},{"ty":"gr","it":[{"ind":0,"ty":"sh","ix":1,"ks":{"a":0,"k":{"i":[[-1.45,0],[0,-1.45],[1.45,0],[0,1.45]],"o":[[1.45,0],[0,1.45],[-1.45,0],[0,-1.45]],"v":[[0,-2.628],[2.626,-0.002],[0,2.624],[-2.626,-0.002]],"c":true},"ix":2},"nm":"패스 1","mn":"ADBE Vector Shape - Group","hd":false},{"ty":"fl","c":{"a":0,"k":[1,1,1,1],"ix":4},"o":{"a":0,"k":100,"ix":5},"r":1,"bm":0,"nm":"칠 1","mn":"ADBE Vector Graphic - Fill","hd":false},{"ty":"tr","p":{"a":0,"k":[169.008,1364.084],"ix":2},"a":{"a":0,"k":[0,0],"ix":1},"s":{"a":0,"k":[100,100],"ix":3},"r":{"a":0,"k":0,"ix":6},"o":{"a":0,"k":100,"ix":7},"sk":{"a":0,"k":0,"ix":4},"sa":{"a":0,"k":0,"ix":5},"nm":"변형"}],"nm":"그룹 9","np":4,"cix":2,"bm":0,"ix":9,"mn":"ADBE Vector Group","hd":false},{"ty":"gr","it":[{"ind":0,"ty":"sh","ix":1,"ks":{"a":0,"k":{"i":[[-1.45,0],[0,-1.45],[1.45,0],[0,1.45]],"o":[[1.45,0],[0,1.45],[-1.45,0],[0,-1.45]],"v":[[0,-2.626],[2.626,0],[0,2.626],[-2.626,0]],"c":true},"ix":2},"nm":"패스 1","mn":"ADBE Vector Shape - Group","hd":false},{"ty":"fl","c":{"a":0,"k":[1,1,1,1],"ix":4},"o":{"a":0,"k":100,"ix":5},"r":1,"bm":0,"nm":"칠 1","mn":"ADBE Vector Graphic - Fill","hd":false},{"ty":"tr","p":{"a":0,"k":[646.944,1424.48],"ix":2},"a":{"a":0,"k":[0,0],"ix":1},"s":{"a":0,"k":[100,100],"ix":3},"r":{"a":0,"k":0,"ix":6},"o":{"a":0,"k":100,"ix":7},"sk":{"a":0,"k":0,"ix":4},"sa":{"a":0,"k":0,"ix":5},"nm":"변형"}],"nm":"그룹 10","np":4,"cix":2,"bm":0,"ix":10,"mn":"ADBE Vector Group","hd":false},{"ty":"gr","it":[{"ind":0,"ty":"sh","ix":1,"ks":{"a":0,"k":{"i":[[-1.45,0],[0,-1.45],[1.45,0],[0,1.45]],"o":[[1.45,0],[0,1.45],[-1.45,0],[0,-1.45]],"v":[[0,-2.625],[2.626,0.001],[0,2.627],[-2.626,0.001]],"c":true},"ix":2},"nm":"패스 1","mn":"ADBE Vector Shape - Group","hd":false},{"ty":"fl","c":{"a":0,"k":[1,1,1,1],"ix":4},"o":{"a":0,"k":100,"ix":5},"r":1,"bm":0,"nm":"칠 1","mn":"ADBE Vector Graphic - Fill","hd":false},{"ty":"tr","p":{"a":0,"k":[909.547,938.665],"ix":2},"a":{"a":0,"k":[0,0],"ix":1},"s":{"a":0,"k":[100,100],"ix":3},"r":{"a":0,"k":0,"ix":6},"o":{"a":0,"k":100,"ix":7},"sk":{"a":0,"k":0,"ix":4},"sa":{"a":0,"k":0,"ix":5},"nm":"변형"}],"nm":"그룹 11","np":4,"cix":2,"bm":0,"ix":11,"mn":"ADBE Vector Group","hd":false},{"ty":"gr","it":[{"ind":0,"ty":"sh","ix":1,"ks":{"a":0,"k":{"i":[[-1.45,0],[0,-1.45],[1.45,0],[0,1.45]],"o":[[1.45,0],[0,1.45],[-1.45,0],[0,-1.45]],"v":[[0,-2.624],[2.626,0.002],[0,2.628],[-2.626,0.002]],"c":true},"ix":2},"nm":"패스 1","mn":"ADBE Vector Shape - Group","hd":false},{"ty":"fl","c":{"a":0,"k":[1,1,1,1],"ix":4},"o":{"a":0,"k":100,"ix":5},"r":1,"bm":0,"nm":"칠 1","mn":"ADBE Vector Graphic - Fill","hd":false},{"ty":"tr","p":{"a":0,"k":[846.522,673.436],"ix":2},"a":{"a":0,"k":[0,0],"ix":1},"s":{"a":0,"k":[100,100],"ix":3},"r":{"a":0,"k":0,"ix":6},"o":{"a":0,"k":100,"ix":7},"sk":{"a":0,"k":0,"ix":4},"sa":{"a":0,"k":0,"ix":5},"nm":"변형"}],"nm":"그룹 12","np":4,"cix":2,"bm":0,"ix":12,"mn":"ADBE Vector Group","hd":false},{"ty":"gr","it":[{"ind":0,"ty":"sh","ix":1,"ks":{"a":0,"k":{"i":[[-1.45,0],[0,-1.45],[1.45,0],[0,1.45]],"o":[[1.45,0],[0,1.45],[-1.45,0],[0,-1.45]],"v":[[0,-2.626],[2.626,0],[0,2.626],[-2.626,0]],"c":true},"ix":2},"nm":"패스 1","mn":"ADBE Vector Shape - Group","hd":false},{"ty":"fl","c":{"a":0,"k":[1,1,1,1],"ix":4},"o":{"a":0,"k":100,"ix":5},"r":1,"bm":0,"nm":"칠 1","mn":"ADBE Vector Graphic - Fill","hd":false},{"ty":"tr","p":{"a":0,"k":[452.618,796.86],"ix":2},"a":{"a":0,"k":[0,0],"ix":1},"s":{"a":0,"k":[100,100],"ix":3},"r":{"a":0,"k":0,"ix":6},"o":{"a":0,"k":100,"ix":7},"sk":{"a":0,"k":0,"ix":4},"sa":{"a":0,"k":0,"ix":5},"nm":"변형"}],"nm":"그룹 13","np":4,"cix":2,"bm":0,"ix":13,"mn":"ADBE Vector Group","hd":false},{"ty":"gr","it":[{"ind":0,"ty":"sh","ix":1,"ks":{"a":0,"k":{"i":[[-1.45,0],[0,-1.45],[1.45,0],[0,1.45]],"o":[[1.45,0],[0,1.45],[-1.45,0],[0,-1.45]],"v":[[0,-2.625],[2.626,0.001],[0,2.627],[-2.626,0.001]],"c":true},"ix":2},"nm":"패스 1","mn":"ADBE Vector Shape - Group","hd":false},{"ty":"fl","c":{"a":0,"k":[1,1,1,1],"ix":4},"o":{"a":0,"k":100,"ix":5},"r":1,"bm":0,"nm":"칠 1","mn":"ADBE Vector Graphic - Fill","hd":false},{"ty":"tr","p":{"a":0,"k":[66.593,634.046],"ix":2},"a":{"a":0,"k":[0,0],"ix":1},"s":{"a":0,"k":[100,100],"ix":3},"r":{"a":0,"k":0,"ix":6},"o":{"a":0,"k":100,"ix":7},"sk":{"a":0,"k":0,"ix":4},"sa":{"a":0,"k":0,"ix":5},"nm":"변형"}],"nm":"그룹 14","np":4,"cix":2,"bm":0,"ix":14,"mn":"ADBE Vector Group","hd":false},{"ty":"gr","it":[{"ind":0,"ty":"sh","ix":1,"ks":{"a":0,"k":{"i":[[-0.725,0],[0,-0.725],[0.725,0],[0,0.725]],"o":[[0.725,0],[0,0.725],[-0.725,0],[0,-0.725]],"v":[[0,-1.313],[1.313,0],[0,1.313],[-1.313,0]],"c":true},"ix":2},"nm":"패스 1","mn":"ADBE Vector Shape - Group","hd":false},{"ty":"fl","c":{"a":0,"k":[1,1,1,1],"ix":4},"o":{"a":0,"k":100,"ix":5},"r":1,"bm":0,"nm":"칠 1","mn":"ADBE Vector Graphic - Fill","hd":false},{"ty":"tr","p":{"a":0,"k":[214.963,987.247],"ix":2},"a":{"a":0,"k":[0,0],"ix":1},"s":{"a":0,"k":[100,100],"ix":3},"r":{"a":0,"k":0,"ix":6},"o":{"a":0,"k":100,"ix":7},"sk":{"a":0,"k":0,"ix":4},"sa":{"a":0,"k":0,"ix":5},"nm":"변형"}],"nm":"그룹 15","np":4,"cix":2,"bm":0,"ix":15,"mn":"ADBE Vector Group","hd":false}],"ip":0,"op":239.00000973467,"st":0,"bm":0},{"ddd":0,"ind":10,"ty":4,"nm":"별1","sr":1,"ks":{"o":{"a":1,"k":[{"i":{"x":[0.833],"y":[0.833]},"o":{"x":[0.167],"y":[0.167]},"t":0,"s":[80]},{"i":{"x":[0.833],"y":[0.833]},"o":{"x":[0.167],"y":[0.167]},"t":67,"s":[30]},{"i":{"x":[0.833],"y":[0.833]},"o":{"x":[0.167],"y":[0.167]},"t":134,"s":[80]},{"i":{"x":[0.833],"y":[0.833]},"o":{"x":[0.167],"y":[0.167]},"t":190,"s":[30]},{"t":239.00000973467,"s":[80]}],"ix":11},"r":{"a":0,"k":0,"ix":10},"p":{"a":0,"k":[562,1218,0],"ix":2},"a":{"a":0,"k":[562.5,1218,0],"ix":1},"s":{"a":0,"k":[100,100,100],"ix":6}},"ao":0,"shapes":[{"ty":"gr","it":[{"ind":0,"ty":"sh","ix":1,"ks":{"a":0,"k":{"i":[[-0.725,0],[0,-0.725],[0.725,0],[0,0.725]],"o":[[0.725,0],[0,0.725],[-0.725,0],[0,-0.725]],"v":[[0,-1.313],[1.313,0],[0,1.313],[-1.313,0]],"c":true},"ix":2},"nm":"패스 1","mn":"ADBE Vector Shape - Group","hd":false},{"ty":"fl","c":{"a":0,"k":[1,1,1,1],"ix":4},"o":{"a":0,"k":100,"ix":5},"r":1,"bm":0,"nm":"칠 1","mn":"ADBE Vector Graphic - Fill","hd":false},{"ty":"tr","p":{"a":0,"k":[1065.795,1034.516],"ix":2},"a":{"a":0,"k":[0,0],"ix":1},"s":{"a":0,"k":[100,100],"ix":3},"r":{"a":0,"k":0,"ix":6},"o":{"a":0,"k":100,"ix":7},"sk":{"a":0,"k":0,"ix":4},"sa":{"a":0,"k":0,"ix":5},"nm":"변형"}],"nm":"그룹 1","np":4,"cix":2,"bm":0,"ix":1,"mn":"ADBE Vector Group","hd":false},{"ty":"gr","it":[{"ind":0,"ty":"sh","ix":1,"ks":{"a":0,"k":{"i":[[-0.725,0],[0,-0.725],[0.725,0],[0,0.725]],"o":[[0.725,0],[0,0.725],[-0.725,0],[0,-0.725]],"v":[[0,-1.313],[1.313,0],[0,1.313],[-1.313,0]],"c":true},"ix":2},"nm":"패스 1","mn":"ADBE Vector Shape - Group","hd":false},{"ty":"fl","c":{"a":0,"k":[1,1,1,1],"ix":4},"o":{"a":0,"k":100,"ix":5},"r":1,"bm":0,"nm":"칠 1","mn":"ADBE Vector Graphic - Fill","hd":false},{"ty":"tr","p":{"a":0,"k":[905.607,1129.053],"ix":2},"a":{"a":0,"k":[0,0],"ix":1},"s":{"a":0,"k":[100,100],"ix":3},"r":{"a":0,"k":0,"ix":6},"o":{"a":0,"k":100,"ix":7},"sk":{"a":0,"k":0,"ix":4},"sa":{"a":0,"k":0,"ix":5},"nm":"변형"}],"nm":"그룹 2","np":4,"cix":2,"bm":0,"ix":2,"mn":"ADBE Vector Group","hd":false},{"ty":"gr","it":[{"ind":0,"ty":"sh","ix":1,"ks":{"a":0,"k":{"i":[[-0.725,0],[0,-0.725],[0.725,0],[0,0.725]],"o":[[0.725,0],[0,0.725],[-0.725,0],[0,-0.725]],"v":[[0,-1.314],[1.313,-0.001],[0,1.312],[-1.313,-0.001]],"c":true},"ix":2},"nm":"패스 1","mn":"ADBE Vector Shape - Group","hd":false},{"ty":"fl","c":{"a":0,"k":[1,1,1,1],"ix":4},"o":{"a":0,"k":100,"ix":5},"r":1,"bm":0,"nm":"칠 1","mn":"ADBE Vector Graphic - Fill","hd":false},{"ty":"tr","p":{"a":0,"k":[432.923,504.06],"ix":2},"a":{"a":0,"k":[0,0],"ix":1},"s":{"a":0,"k":[100,100],"ix":3},"r":{"a":0,"k":0,"ix":6},"o":{"a":0,"k":100,"ix":7},"sk":{"a":0,"k":0,"ix":4},"sa":{"a":0,"k":0,"ix":5},"nm":"변형"}],"nm":"그룹 3","np":4,"cix":2,"bm":0,"ix":3,"mn":"ADBE Vector Group","hd":false},{"ty":"gr","it":[{"ind":0,"ty":"sh","ix":1,"ks":{"a":0,"k":{"i":[[-0.725,0],[0,-0.725],[0.725,0],[0,0.725]],"o":[[0.725,0],[0,0.725],[-0.725,0],[0,-0.725]],"v":[[0,-1.313],[1.313,0],[0,1.313],[-1.313,0]],"c":true},"ix":2},"nm":"패스 1","mn":"ADBE Vector Shape - Group","hd":false},{"ty":"fl","c":{"a":0,"k":[1,1,1,1],"ix":4},"o":{"a":0,"k":100,"ix":5},"r":1,"bm":0,"nm":"칠 1","mn":"ADBE Vector Graphic - Fill","hd":false},{"ty":"tr","p":{"a":0,"k":[1039.535,693.133],"ix":2},"a":{"a":0,"k":[0,0],"ix":1},"s":{"a":0,"k":[100,100],"ix":3},"r":{"a":0,"k":0,"ix":6},"o":{"a":0,"k":100,"ix":7},"sk":{"a":0,"k":0,"ix":4},"sa":{"a":0,"k":0,"ix":5},"nm":"변형"}],"nm":"그룹 4","np":4,"cix":2,"bm":0,"ix":4,"mn":"ADBE Vector Group","hd":false},{"ty":"gr","it":[{"ind":0,"ty":"sh","ix":1,"ks":{"a":0,"k":{"i":[[-0.725,0],[0,-0.725],[0.725,0],[0,0.725]],"o":[[0.725,0],[0,0.725],[-0.725,0],[0,-0.725]],"v":[[0,-1.311],[1.313,0.002],[0,1.315],[-1.313,0.002]],"c":true},"ix":2},"nm":"패스 1","mn":"ADBE Vector Shape - Group","hd":false},{"ty":"fl","c":{"a":0,"k":[1,1,1,1],"ix":4},"o":{"a":0,"k":100,"ix":5},"r":1,"bm":0,"nm":"칠 1","mn":"ADBE Vector Graphic - Fill","hd":false},{"ty":"tr","p":{"a":0,"k":[916.112,792.92],"ix":2},"a":{"a":0,"k":[0,0],"ix":1},"s":{"a":0,"k":[100,100],"ix":3},"r":{"a":0,"k":0,"ix":6},"o":{"a":0,"k":100,"ix":7},"sk":{"a":0,"k":0,"ix":4},"sa":{"a":0,"k":0,"ix":5},"nm":"변형"}],"nm":"그룹 5","np":4,"cix":2,"bm":0,"ix":5,"mn":"ADBE Vector Group","hd":false},{"ty":"gr","it":[{"ind":0,"ty":"sh","ix":1,"ks":{"a":0,"k":{"i":[[-0.725,0],[0,-0.725],[0.725,0],[0,0.725]],"o":[[0.725,0],[0,0.725],[-0.725,0],[0,-0.725]],"v":[[0,-1.313],[1.313,0],[0,1.313],[-1.313,0]],"c":true},"ix":2},"nm":"패스 1","mn":"ADBE Vector Shape - Group","hd":false},{"ty":"fl","c":{"a":0,"k":[1,1,1,1],"ix":4},"o":{"a":0,"k":100,"ix":5},"r":1,"bm":0,"nm":"칠 1","mn":"ADBE Vector Graphic - Fill","hd":false},{"ty":"tr","p":{"a":0,"k":[262.231,664.246],"ix":2},"a":{"a":0,"k":[0,0],"ix":1},"s":{"a":0,"k":[100,100],"ix":3},"r":{"a":0,"k":0,"ix":6},"o":{"a":0,"k":100,"ix":7},"sk":{"a":0,"k":0,"ix":4},"sa":{"a":0,"k":0,"ix":5},"nm":"변형"}],"nm":"그룹 6","np":4,"cix":2,"bm":0,"ix":6,"mn":"ADBE Vector Group","hd":false},{"ty":"gr","it":[{"ind":0,"ty":"sh","ix":1,"ks":{"a":0,"k":{"i":[[-0.725,0],[0,-0.725],[0.725,0],[0,0.725]],"o":[[0.725,0],[0,0.725],[-0.725,0],[0,-0.725]],"v":[[0,-1.313],[1.313,0],[0,1.313],[-1.313,0]],"c":true},"ix":2},"nm":"패스 1","mn":"ADBE Vector Shape - Group","hd":false},{"ty":"fl","c":{"a":0,"k":[1,1,1,1],"ix":4},"o":{"a":0,"k":100,"ix":5},"r":1,"bm":0,"nm":"칠 1","mn":"ADBE Vector Graphic - Fill","hd":false},{"ty":"tr","p":{"a":0,"k":[235.971,630.107],"ix":2},"a":{"a":0,"k":[0,0],"ix":1},"s":{"a":0,"k":[100,100],"ix":3},"r":{"a":0,"k":0,"ix":6},"o":{"a":0,"k":100,"ix":7},"sk":{"a":0,"k":0,"ix":4},"sa":{"a":0,"k":0,"ix":5},"nm":"변형"}],"nm":"그룹 7","np":4,"cix":2,"bm":0,"ix":7,"mn":"ADBE Vector Group","hd":false},{"ty":"gr","it":[{"ind":0,"ty":"sh","ix":1,"ks":{"a":0,"k":{"i":[[-1.45,0],[0,-1.45],[1.45,0],[0,1.45]],"o":[[1.45,0],[0,1.45],[-1.45,0],[0,-1.45]],"v":[[0,-2.626],[2.626,0],[0,2.626],[-2.626,0]],"c":true},"ix":2},"nm":"패스 1","mn":"ADBE Vector Shape - Group","hd":false},{"ty":"fl","c":{"a":0,"k":[1,1,1,1],"ix":4},"o":{"a":0,"k":100,"ix":5},"r":1,"bm":0,"nm":"칠 1","mn":"ADBE Vector Graphic - Fill","hd":false},{"ty":"tr","p":{"a":0,"k":[780.871,1834.14],"ix":2},"a":{"a":0,"k":[0,0],"ix":1},"s":{"a":0,"k":[100,100],"ix":3},"r":{"a":0,"k":0,"ix":6},"o":{"a":0,"k":100,"ix":7},"sk":{"a":0,"k":0,"ix":4},"sa":{"a":0,"k":0,"ix":5},"nm":"변형"}],"nm":"그룹 8","np":4,"cix":2,"bm":0,"ix":8,"mn":"ADBE Vector Group","hd":false},{"ty":"gr","it":[{"ind":0,"ty":"sh","ix":1,"ks":{"a":0,"k":{"i":[[-1.45,0],[0,-1.45],[1.45,0],[0,1.45]],"o":[[1.45,0],[0,1.45],[-1.45,0],[0,-1.45]],"v":[[0,-2.626],[2.626,0],[0,2.626],[-2.626,0]],"c":true},"ix":2},"nm":"패스 1","mn":"ADBE Vector Shape - Group","hd":false},{"ty":"fl","c":{"a":0,"k":[1,1,1,1],"ix":4},"o":{"a":0,"k":100,"ix":5},"r":1,"bm":0,"nm":"칠 1","mn":"ADBE Vector Graphic - Fill","hd":false},{"ty":"tr","p":{"a":0,"k":[56.089,1642.44],"ix":2},"a":{"a":0,"k":[0,0],"ix":1},"s":{"a":0,"k":[100,100],"ix":3},"r":{"a":0,"k":0,"ix":6},"o":{"a":0,"k":100,"ix":7},"sk":{"a":0,"k":0,"ix":4},"sa":{"a":0,"k":0,"ix":5},"nm":"변형"}],"nm":"그룹 9","np":4,"cix":2,"bm":0,"ix":9,"mn":"ADBE Vector Group","hd":false},{"ty":"gr","it":[{"ind":0,"ty":"sh","ix":1,"ks":{"a":0,"k":{"i":[[-1.45,0],[0,-1.45],[1.45,0],[0,1.45]],"o":[[1.45,0],[0,1.45],[-1.45,0],[0,-1.45]],"v":[[0,-2.626],[2.626,0],[0,2.626],[-2.626,0]],"c":true},"ix":2},"nm":"패스 1","mn":"ADBE Vector Shape - Group","hd":false},{"ty":"fl","c":{"a":0,"k":[1,1,1,1],"ix":4},"o":{"a":0,"k":100,"ix":5},"r":1,"bm":0,"nm":"칠 1","mn":"ADBE Vector Graphic - Fill","hd":false},{"ty":"tr","p":{"a":0,"k":[368.585,1910.295],"ix":2},"a":{"a":0,"k":[0,0],"ix":1},"s":{"a":0,"k":[100,100],"ix":3},"r":{"a":0,"k":0,"ix":6},"o":{"a":0,"k":100,"ix":7},"sk":{"a":0,"k":0,"ix":4},"sa":{"a":0,"k":0,"ix":5},"nm":"변형"}],"nm":"그룹 10","np":4,"cix":2,"bm":0,"ix":10,"mn":"ADBE Vector Group","hd":false}],"ip":0,"op":239.00000973467,"st":0,"bm":0},{"ddd":0,"ind":11,"ty":4,"nm":"배경","sr":1,"ks":{"o":{"a":0,"k":100,"ix":11},"r":{"a":0,"k":0,"ix":10},"p":{"a":0,"k":[562,1218,0],"ix":2},"a":{"a":0,"k":[562.5,1218,0],"ix":1},"s":{"a":0,"k":[100,100,100],"ix":6}},"ao":0,"shapes":[{"ty":"gr","it":[{"ind":0,"ty":"sh","ix":1,"ks":{"a":0,"k":{"i":[[0,0],[0,0],[0,0],[0,0]],"o":[[0,0],[0,0],[0,0],[0,0]],"v":[[-562.5,1218],[562.5,1218],[562.5,-1218],[-562.5,-1218]],"c":true},"ix":2},"nm":"패스 1","mn":"ADBE Vector Shape - Group","hd":false},{"ind":1,"ty":"sh","ix":2,"ks":{"a":0,"k":{"i":[[0,0],[0,0],[0,0],[0,0]],"o":[[0,0],[0,0],[0,0],[0,0]],"v":[[-560.5,1215.561],[562.5,1215.561],[562.5,-1216],[-560.5,-1216]],"c":true},"ix":2},"nm":"패스 2","mn":"ADBE Vector Shape - Group","hd":false},{"ty":"mm","mm":1,"nm":"패스 병합 1","mn":"ADBE Vector Filter - Merge","hd":false},{"ty":"gf","o":{"a":0,"k":100,"ix":10},"r":1,"bm":0,"g":{"p":2,"k":{"a":0,"k":[0,1,1,1,1,0,0,0],"ix":9}},"s":{"a":0,"k":[-1.125,1241.625],"ix":5},"e":{"a":0,"k":[-2.906,-1221.938],"ix":6},"t":1,"nm":"그라디언트 칠 1","mn":"ADBE Vector Graphic - G-Fill","hd":false},{"ty":"tr","p":{"a":0,"k":[562.5,1218],"ix":2},"a":{"a":0,"k":[0,0],"ix":1},"s":{"a":0,"k":[100,100],"ix":3},"r":{"a":0,"k":0,"ix":6},"o":{"a":0,"k":100,"ix":7},"sk":{"a":0,"k":0,"ix":4},"sa":{"a":0,"k":0,"ix":5},"nm":"변형"}],"nm":"그룹 1","np":4,"cix":2,"bm":0,"ix":1,"mn":"ADBE Vector Group","hd":false}],"ip":0,"op":239.00000973467,"st":0,"bm":0}],"markers":[]}