{"v":"4.8.0","meta":{"g":"LottieFiles AE 3.4.3","a":"","k":"","d":"","tc":""},"fr":29.9700012207031,"ip":0,"op":90.0000036657751,"w":1125,"h":2436,"nm":"레이어 1/0404_MatchingLoadingView","ddd":0,"assets":[{"id":"image_0","w":184,"h":193,"u":"","p":"image_0.png","e":1},{"id":"comp_0","layers":[{"ddd":0,"ind":1,"ty":2,"nm":"레이어 1","refId":"image_0","sr":1,"ks":{"o":{"a":0,"k":100,"ix":11},"r":{"a":0,"k":0,"ix":10},"p":{"a":0,"k":[471.805,726.71,0],"ix":2},"a":{"a":0,"k":[91.672,96.141,0],"ix":1},"s":{"a":0,"k":[100,100,100],"ix":6}},"ao":0,"ip":0,"op":300.00001221925,"st":0,"bm":0}]}],"layers":[{"ddd":0,"ind":1,"ty":4,"nm":"산 3","sr":1,"ks":{"o":{"a":0,"k":100,"ix":11},"r":{"a":0,"k":0,"ix":10},"p":{"a":0,"k":[1326.5,742,0],"ix":2},"a":{"a":0,"k":[562.5,1250,0],"ix":1},"s":{"a":0,"k":[100,100,100],"ix":6}},"ao":0,"shapes":[{"ty":"gr","it":[{"ind":0,"ty":"sh","ix":1,"ks":{"a":0,"k":{"i":[[0,0],[-135.934,-75.65],[0,0],[173.73,0],[0,0],[-152.155,83.846]],"o":[[78.296,-49.65],[0,0],[152.157,83.846],[0,0],[-173.73,0],[0,0]],"v":[[-426.064,-244.355],[-101.834,-240.355],[288.518,-19.078],[207.402,296.182],[-697.3,296.182],[-902.415,66.922]],"c":true},"ix":2},"nm":"패스 1","mn":"ADBE Vector Shape - Group","hd":false},{"ty":"mm","mm":4,"nm":"패스 병합 1","mn":"ADBE Vector Filter - Merge","hd":false},{"ty":"fl","c":{"a":0,"k":[0.201940917969,0.185784777473,0.246369485294,1],"ix":4},"o":{"a":0,"k":100,"ix":5},"r":1,"bm":0,"nm":"칠 1","mn":"ADBE Vector Graphic - Fill","hd":false},{"ty":"tr","p":{"a":0,"k":[138.331,2713.24],"ix":2},"a":{"a":0,"k":[0,0],"ix":1},"s":{"a":0,"k":[100,100],"ix":3},"r":{"a":0,"k":0,"ix":6},"o":{"a":0,"k":100,"ix":7},"sk":{"a":0,"k":0,"ix":4},"sa":{"a":0,"k":0,"ix":5},"nm":"변형"}],"nm":"그룹 3","np":3,"cix":2,"bm":0,"ix":1,"mn":"ADBE Vector Group","hd":false}],"ip":0,"op":90.0000036657751,"st":0,"bm":0},{"ddd":0,"ind":2,"ty":4,"nm":"산 2","sr":1,"ks":{"o":{"a":0,"k":100,"ix":11},"r":{"a":0,"k":0,"ix":10},"p":{"a":0,"k":[1768.5,714,0],"ix":2},"a":{"a":0,"k":[562.5,1250,0],"ix":1},"s":{"a":0,"k":[100,100,100],"ix":6}},"ao":0,"shapes":[{"ty":"gr","it":[{"ind":0,"ty":"sh","ix":1,"ks":{"a":0,"k":{"i":[[0,0],[-135.934,-75.65],[0,0],[173.73,0],[0,0],[-152.155,83.846]],"o":[[78.296,-49.65],[0,0],[152.157,83.846],[0,0],[-173.73,0],[0,0]],"v":[[-426.064,-244.355],[-101.834,-240.355],[288.518,-19.078],[207.402,296.182],[-697.3,296.182],[-902.415,66.922]],"c":true},"ix":2},"nm":"패스 1","mn":"ADBE Vector Shape - Group","hd":false},{"ty":"mm","mm":4,"nm":"패스 병합 1","mn":"ADBE Vector Filter - Merge","hd":false},{"ty":"fl","c":{"a":0,"k":[0.18014384251,0.163765357522,0.225183823529,1],"ix":4},"o":{"a":0,"k":100,"ix":5},"r":1,"bm":0,"nm":"칠 1","mn":"ADBE Vector Graphic - Fill","hd":false},{"ty":"tr","p":{"a":0,"k":[137.893,2704.99],"ix":2},"a":{"a":0,"k":[0,0],"ix":1},"s":{"a":0,"k":[100,100],"ix":3},"r":{"a":0,"k":0,"ix":6},"o":{"a":0,"k":100,"ix":7},"sk":{"a":0,"k":0,"ix":4},"sa":{"a":0,"k":0,"ix":5},"nm":"변형"}],"nm":"그룹 3","np":3,"cix":2,"bm":0,"ix":1,"mn":"ADBE Vector Group","hd":false}],"ip":0,"op":90.0000036657751,"st":0,"bm":0},{"ddd":0,"ind":3,"ty":4,"nm":"산","sr":1,"ks":{"o":{"a":0,"k":100,"ix":11},"r":{"a":0,"k":0,"ix":10},"p":{"a":0,"k":[944.5,682,0],"ix":2},"a":{"a":0,"k":[562.5,1250,0],"ix":1},"s":{"a":0,"k":[100,100,100],"ix":6}},"ao":0,"shapes":[{"ty":"gr","it":[{"ind":0,"ty":"sh","ix":1,"ks":{"a":0,"k":{"i":[[0,0],[-50.496,-27.827],[0,0],[173.73,0],[0,0],[-152.155,83.846]],"o":[[50.497,-27.827],[0,0],[152.157,83.846],[0,0],[-173.73,0],[0,0]],"v":[[-326.064,-268.355],[-163.834,-268.355],[288.518,-19.078],[207.402,296.182],[-697.3,296.182],[-778.415,-19.078]],"c":true},"ix":2},"nm":"패스 1","mn":"ADBE Vector Shape - Group","hd":false},{"ty":"mm","mm":4,"nm":"패스 병합 1","mn":"ADBE Vector Filter - Merge","hd":false},{"ty":"fl","c":{"a":0,"k":[0.163399939444,0.149054433785,0.202849264706,1],"ix":4},"o":{"a":0,"k":100,"ix":5},"r":1,"bm":0,"nm":"칠 1","mn":"ADBE Vector Graphic - Fill","hd":false},{"ty":"tr","p":{"a":0,"k":[129.768,2704.005],"ix":2},"a":{"a":0,"k":[0,0],"ix":1},"s":{"a":0,"k":[100,100],"ix":3},"r":{"a":0,"k":0,"ix":6},"o":{"a":0,"k":100,"ix":7},"sk":{"a":0,"k":0,"ix":4},"sa":{"a":0,"k":0,"ix":5},"nm":"변형"}],"nm":"그룹 3","np":3,"cix":2,"bm":0,"ix":1,"mn":"ADBE Vector Group","hd":false}],"ip":0,"op":90.0000036657751,"st":0,"bm":0},{"ddd":0,"ind":4,"ty":0,"nm":"FallingStars 3","refId":"comp_0","sr":1,"ks":{"o":{"a":1,"k":[{"i":{"x":[0.833],"y":[1]},"o":{"x":[0.167],"y":[0]},"t":26,"s":[0]},{"i":{"x":[1],"y":[1]},"o":{"x":[0.333],"y":[0]},"t":27,"s":[60]},{"t":57.0000023216576,"s":[0]}],"ix":11},"r":{"a":0,"k":0,"ix":10},"p":{"a":1,"k":[{"i":{"x":0.667,"y":1},"o":{"x":0.333,"y":0},"t":27,"s":[1336,1600,0],"to":[0,0,0],"ti":[0,0,0]},{"t":57.0000023216576,"s":[664,2400,0]}],"ix":2},"a":{"a":0,"k":[562.5,1218,0],"ix":1},"s":{"a":0,"k":[80,80,100],"ix":6}},"ao":0,"w":1125,"h":2436,"ip":0,"op":300.00001221925,"st":0,"bm":0},{"ddd":0,"ind":5,"ty":0,"nm":"FallingStars 3","refId":"comp_0","sr":1,"ks":{"o":{"a":1,"k":[{"i":{"x":[0.833],"y":[1]},"o":{"x":[0.167],"y":[0]},"t":9,"s":[0]},{"i":{"x":[1],"y":[1]},"o":{"x":[0.333],"y":[0]},"t":10,"s":[60]},{"t":31.0000012626559,"s":[0]}],"ix":11},"r":{"a":0,"k":0,"ix":10},"p":{"a":1,"k":[{"i":{"x":0.667,"y":1},"o":{"x":0.333,"y":0},"t":10,"s":[836,1448,0],"to":[0,0,0],"ti":[0,0,0]},{"t":31.0000012626559,"s":[335,1948,0]}],"ix":2},"a":{"a":0,"k":[562.5,1218,0],"ix":1},"s":{"a":0,"k":[70,70,100],"ix":6}},"ao":0,"w":1125,"h":2436,"ip":0,"op":300.00001221925,"st":0,"bm":0},{"ddd":0,"ind":6,"ty":0,"nm":"FallingStars 3","refId":"comp_0","sr":1,"ks":{"o":{"a":1,"k":[{"i":{"x":[1],"y":[1]},"o":{"x":[0.333],"y":[0]},"t":0,"s":[100]},{"t":17.0000006924242,"s":[0]}],"ix":11},"r":{"a":0,"k":0,"ix":10},"p":{"a":1,"k":[{"i":{"x":0.667,"y":1},"o":{"x":0.333,"y":0},"t":0,"s":[1290.5,634,0],"to":[0,0,0],"ti":[0,0,0]},{"t":10.0000004073083,"s":[562.5,1218,0]}],"ix":2},"a":{"a":0,"k":[562.5,1218,0],"ix":1},"s":{"a":0,"k":[100,100,100],"ix":6}},"ao":0,"w":1125,"h":2436,"ip":0,"op":300.00001221925,"st":0,"bm":0},{"ddd":0,"ind":7,"ty":4,"nm":"별3","sr":1,"ks":{"o":{"a":1,"k":[{"i":{"x":[0.833],"y":[0.833]},"o":{"x":[0.167],"y":[0.167]},"t":0,"s":[50]},{"i":{"x":[0.833],"y":[0.833]},"o":{"x":[0.167],"y":[0.167]},"t":41,"s":[80]},{"i":{"x":[0.833],"y":[0.833]},"o":{"x":[0.167],"y":[0.167]},"t":77,"s":[50]},{"i":{"x":[0.833],"y":[0.833]},"o":{"x":[0.167],"y":[0.167]},"t":115,"s":[80]},{"i":{"x":[0.833],"y":[0.833]},"o":{"x":[0.167],"y":[0.167]},"t":149,"s":[50]},{"i":{"x":[0.833],"y":[0.833]},"o":{"x":[0.167],"y":[0.167]},"t":186,"s":[80]},{"i":{"x":[0.833],"y":[0.833]},"o":{"x":[0.167],"y":[0.167]},"t":220,"s":[50]},{"i":{"x":[0.833],"y":[0.833]},"o":{"x":[0.167],"y":[0.167]},"t":264,"s":[80]},{"t":298.000012137789,"s":[50]}],"ix":11},"r":{"a":0,"k":0,"ix":10},"p":{"a":0,"k":[562,1218,0],"ix":2},"a":{"a":0,"k":[562.5,1218,0],"ix":1},"s":{"a":0,"k":[100,100,100],"ix":6}},"ao":0,"shapes":[{"ty":"gr","it":[{"ind":0,"ty":"sh","ix":1,"ks":{"a":0,"k":{"i":[[-0.725,0],[0,-0.725],[0.725,0],[0,0.725]],"o":[[0.725,0],[0,0.725],[-0.725,0],[0,-0.725]],"v":[[0,-1.313],[1.313,0],[0,1.313],[-1.313,0]],"c":true},"ix":2},"nm":"패스 1","mn":"ADBE Vector Shape - Group","hd":false},{"ty":"fl","c":{"a":0,"k":[1,1,1,1],"ix":4},"o":{"a":0,"k":100,"ix":5},"r":1,"bm":0,"nm":"칠 1","mn":"ADBE Vector Graphic - Fill","hd":false},{"ty":"tr","p":{"a":0,"k":[962.067,1863.027],"ix":2},"a":{"a":0,"k":[0,0],"ix":1},"s":{"a":0,"k":[100,100],"ix":3},"r":{"a":0,"k":0,"ix":6},"o":{"a":0,"k":100,"ix":7},"sk":{"a":0,"k":0,"ix":4},"sa":{"a":0,"k":0,"ix":5},"nm":"변형"}],"nm":"그룹 1","np":4,"cix":2,"bm":0,"ix":1,"mn":"ADBE Vector Group","hd":false},{"ty":"gr","it":[{"ind":0,"ty":"sh","ix":1,"ks":{"a":0,"k":{"i":[[-0.725,0],[0,-0.725],[0.725,0],[0,0.725]],"o":[[0.725,0],[0,0.725],[-0.725,0],[0,-0.725]],"v":[[0,-1.313],[1.313,0],[0,1.313],[-1.313,0]],"c":true},"ix":2},"nm":"패스 1","mn":"ADBE Vector Shape - Group","hd":false},{"ty":"fl","c":{"a":0,"k":[1,1,1,1],"ix":4},"o":{"a":0,"k":100,"ix":5},"r":1,"bm":0,"nm":"칠 1","mn":"ADBE Vector Graphic - Fill","hd":false},{"ty":"tr","p":{"a":0,"k":[90.227,1973.32],"ix":2},"a":{"a":0,"k":[0,0],"ix":1},"s":{"a":0,"k":[100,100],"ix":3},"r":{"a":0,"k":0,"ix":6},"o":{"a":0,"k":100,"ix":7},"sk":{"a":0,"k":0,"ix":4},"sa":{"a":0,"k":0,"ix":5},"nm":"변형"}],"nm":"그룹 2","np":4,"cix":2,"bm":0,"ix":2,"mn":"ADBE Vector Group","hd":false},{"ty":"gr","it":[{"ind":0,"ty":"sh","ix":1,"ks":{"a":0,"k":{"i":[[-0.725,0],[0,-0.725],[0.725,0],[0,0.725]],"o":[[0.725,0],[0,0.725],[-0.725,0],[0,-0.725]],"v":[[0,-1.313],[1.313,0],[0,1.313],[-1.313,0]],"c":true},"ix":2},"nm":"패스 1","mn":"ADBE Vector Shape - Group","hd":false},{"ty":"fl","c":{"a":0,"k":[1,1,1,1],"ix":4},"o":{"a":0,"k":100,"ix":5},"r":1,"bm":0,"nm":"칠 1","mn":"ADBE Vector Graphic - Fill","hd":false},{"ty":"tr","p":{"a":0,"k":[145.373,1834.14],"ix":2},"a":{"a":0,"k":[0,0],"ix":1},"s":{"a":0,"k":[100,100],"ix":3},"r":{"a":0,"k":0,"ix":6},"o":{"a":0,"k":100,"ix":7},"sk":{"a":0,"k":0,"ix":4},"sa":{"a":0,"k":0,"ix":5},"nm":"변형"}],"nm":"그룹 3","np":4,"cix":2,"bm":0,"ix":3,"mn":"ADBE Vector Group","hd":false},{"ty":"gr","it":[{"ind":0,"ty":"sh","ix":1,"ks":{"a":0,"k":{"i":[[-0.725,0],[0,-0.725],[0.725,0],[0,0.725]],"o":[[0.725,0],[0,0.725],[-0.725,0],[0,-0.725]],"v":[[0,-1.313],[1.313,0],[0,1.313],[-1.313,0]],"c":true},"ix":2},"nm":"패스 1","mn":"ADBE Vector Shape - Group","hd":false},{"ty":"fl","c":{"a":0,"k":[1,1,1,1],"ix":4},"o":{"a":0,"k":100,"ix":5},"r":1,"bm":0,"nm":"칠 1","mn":"ADBE Vector Graphic - Fill","hd":false},{"ty":"tr","p":{"a":0,"k":[772.993,1645.066],"ix":2},"a":{"a":0,"k":[0,0],"ix":1},"s":{"a":0,"k":[100,100],"ix":3},"r":{"a":0,"k":0,"ix":6},"o":{"a":0,"k":100,"ix":7},"sk":{"a":0,"k":0,"ix":4},"sa":{"a":0,"k":0,"ix":5},"nm":"변형"}],"nm":"그룹 4","np":4,"cix":2,"bm":0,"ix":4,"mn":"ADBE Vector Group","hd":false},{"ty":"gr","it":[{"ind":0,"ty":"sh","ix":1,"ks":{"a":0,"k":{"i":[[-0.725,0],[0,-0.725],[0.725,0],[0,0.725]],"o":[[0.725,0],[0,0.725],[-0.725,0],[0,-0.725]],"v":[[0,-1.313],[1.313,0],[0,1.313],[-1.313,0]],"c":true},"ix":2},"nm":"패스 1","mn":"ADBE Vector Shape - Group","hd":false},{"ty":"fl","c":{"a":0,"k":[1,1,1,1],"ix":4},"o":{"a":0,"k":100,"ix":5},"r":1,"bm":0,"nm":"칠 1","mn":"ADBE Vector Graphic - Fill","hd":false},{"ty":"tr","p":{"a":0,"k":[830.766,1519.017],"ix":2},"a":{"a":0,"k":[0,0],"ix":1},"s":{"a":0,"k":[100,100],"ix":3},"r":{"a":0,"k":0,"ix":6},"o":{"a":0,"k":100,"ix":7},"sk":{"a":0,"k":0,"ix":4},"sa":{"a":0,"k":0,"ix":5},"nm":"변형"}],"nm":"그룹 5","np":4,"cix":2,"bm":0,"ix":5,"mn":"ADBE Vector Group","hd":false},{"ty":"gr","it":[{"ind":0,"ty":"sh","ix":1,"ks":{"a":0,"k":{"i":[[-0.725,0],[0,-0.725],[0.725,0],[0,0.725]],"o":[[0.725,0],[0,0.725],[-0.725,0],[0,-0.725]],"v":[[0,-1.312],[1.313,0.001],[0,1.314],[-1.313,0.001]],"c":true},"ix":2},"nm":"패스 1","mn":"ADBE Vector Shape - Group","hd":false},{"ty":"fl","c":{"a":0,"k":[1,1,1,1],"ix":4},"o":{"a":0,"k":100,"ix":5},"r":1,"bm":0,"nm":"칠 1","mn":"ADBE Vector Graphic - Fill","hd":false},{"ty":"tr","p":{"a":0,"k":[597.05,862.51],"ix":2},"a":{"a":0,"k":[0,0],"ix":1},"s":{"a":0,"k":[100,100],"ix":3},"r":{"a":0,"k":0,"ix":6},"o":{"a":0,"k":100,"ix":7},"sk":{"a":0,"k":0,"ix":4},"sa":{"a":0,"k":0,"ix":5},"nm":"변형"}],"nm":"그룹 6","np":4,"cix":2,"bm":0,"ix":6,"mn":"ADBE Vector Group","hd":false},{"ty":"gr","it":[{"ind":0,"ty":"sh","ix":1,"ks":{"a":0,"k":{"i":[[-0.725,0],[0,-0.725],[0.725,0],[0,0.725]],"o":[[0.725,0],[0,0.725],[-0.725,0],[0,-0.725]],"v":[[0,-1.313],[1.313,0],[0,1.313],[-1.313,0]],"c":true},"ix":2},"nm":"패스 1","mn":"ADBE Vector Shape - Group","hd":false},{"ty":"fl","c":{"a":0,"k":[1,1,1,1],"ix":4},"o":{"a":0,"k":100,"ix":5},"r":1,"bm":0,"nm":"칠 1","mn":"ADBE Vector Graphic - Fill","hd":false},{"ty":"tr","p":{"a":0,"k":[1032.97,442.347],"ix":2},"a":{"a":0,"k":[0,0],"ix":1},"s":{"a":0,"k":[100,100],"ix":3},"r":{"a":0,"k":0,"ix":6},"o":{"a":0,"k":100,"ix":7},"sk":{"a":0,"k":0,"ix":4},"sa":{"a":0,"k":0,"ix":5},"nm":"변형"}],"nm":"그룹 7","np":4,"cix":2,"bm":0,"ix":7,"mn":"ADBE Vector Group","hd":false},{"ty":"gr","it":[{"ind":0,"ty":"sh","ix":1,"ks":{"a":0,"k":{"i":[[-0.725,0],[0,-0.725],[0.725,0],[0,0.725]],"o":[[0.725,0],[0,0.725],[-0.725,0],[0,-0.725]],"v":[[0,-1.313],[1.313,0],[0,1.313],[-1.313,0]],"c":true},"ix":2},"nm":"패스 1","mn":"ADBE Vector Shape - Group","hd":false},{"ty":"fl","c":{"a":0,"k":[1,1,1,1],"ix":4},"o":{"a":0,"k":100,"ix":5},"r":1,"bm":0,"nm":"칠 1","mn":"ADBE Vector Graphic - Fill","hd":false},{"ty":"tr","p":{"a":0,"k":[1030.344,1450.741],"ix":2},"a":{"a":0,"k":[0,0],"ix":1},"s":{"a":0,"k":[100,100],"ix":3},"r":{"a":0,"k":0,"ix":6},"o":{"a":0,"k":100,"ix":7},"sk":{"a":0,"k":0,"ix":4},"sa":{"a":0,"k":0,"ix":5},"nm":"변형"}],"nm":"그룹 8","np":4,"cix":2,"bm":0,"ix":8,"mn":"ADBE Vector Group","hd":false},{"ty":"gr","it":[{"ind":0,"ty":"sh","ix":1,"ks":{"a":0,"k":{"i":[[-0.725,0],[0,-0.725],[0.725,0],[0,0.725]],"o":[[0.725,0],[0,0.725],[-0.725,0],[0,-0.725]],"v":[[0,-1.313],[1.313,0],[0,1.313],[-1.313,0]],"c":true},"ix":2},"nm":"패스 1","mn":"ADBE Vector Shape - Group","hd":false},{"ty":"fl","c":{"a":0,"k":[1,1,1,1],"ix":4},"o":{"a":0,"k":100,"ix":5},"r":1,"bm":0,"nm":"칠 1","mn":"ADBE Vector Graphic - Fill","hd":false},{"ty":"tr","p":{"a":0,"k":[87.601,1125.114],"ix":2},"a":{"a":0,"k":[0,0],"ix":1},"s":{"a":0,"k":[100,100],"ix":3},"r":{"a":0,"k":0,"ix":6},"o":{"a":0,"k":100,"ix":7},"sk":{"a":0,"k":0,"ix":4},"sa":{"a":0,"k":0,"ix":5},"nm":"변형"}],"nm":"그룹 9","np":4,"cix":2,"bm":0,"ix":9,"mn":"ADBE Vector Group","hd":false}],"ip":0,"op":90.0000036657751,"st":0,"bm":0},{"ddd":0,"ind":8,"ty":4,"nm":"별2","sr":1,"ks":{"o":{"a":1,"k":[{"i":{"x":[0.833],"y":[0.833]},"o":{"x":[0.167],"y":[0.167]},"t":0,"s":[30]},{"i":{"x":[0.833],"y":[0.833]},"o":{"x":[0.167],"y":[0.167]},"t":41,"s":[80]},{"i":{"x":[0.833],"y":[0.833]},"o":{"x":[0.167],"y":[0.167]},"t":77,"s":[30]},{"i":{"x":[0.833],"y":[0.833]},"o":{"x":[0.167],"y":[0.167]},"t":115,"s":[80]},{"i":{"x":[0.833],"y":[0.833]},"o":{"x":[0.167],"y":[0.167]},"t":149,"s":[30]},{"i":{"x":[0.833],"y":[0.833]},"o":{"x":[0.167],"y":[0.167]},"t":186,"s":[80]},{"i":{"x":[0.833],"y":[0.833]},"o":{"x":[0.167],"y":[0.167]},"t":220,"s":[30]},{"i":{"x":[0.833],"y":[0.833]},"o":{"x":[0.167],"y":[0.167]},"t":264,"s":[80]},{"t":298.000012137789,"s":[30]}],"ix":11},"r":{"a":0,"k":0,"ix":10},"p":{"a":0,"k":[562,1218,0],"ix":2},"a":{"a":0,"k":[562.5,1218,0],"ix":1},"s":{"a":0,"k":[100,100,100],"ix":6}},"ao":0,"shapes":[{"ty":"gr","it":[{"ind":0,"ty":"sh","ix":1,"ks":{"a":0,"k":{"i":[[-2.175,0],[0,-2.175],[2.175,0],[0,2.176]],"o":[[2.175,0],[0,2.176],[-2.175,0],[0,-2.175]],"v":[[0,-3.939],[3.939,0],[0,3.939],[-3.939,0]],"c":true},"ix":2},"nm":"패스 1","mn":"ADBE Vector Shape - Group","hd":false},{"ty":"fl","c":{"a":0,"k":[1,1,1,1],"ix":4},"o":{"a":0,"k":100,"ix":5},"r":1,"bm":0,"nm":"칠 1","mn":"ADBE Vector Graphic - Fill","hd":false},{"ty":"tr","p":{"a":0,"k":[199.207,879.58],"ix":2},"a":{"a":0,"k":[0,0],"ix":1},"s":{"a":0,"k":[100,100],"ix":3},"r":{"a":0,"k":0,"ix":6},"o":{"a":0,"k":100,"ix":7},"sk":{"a":0,"k":0,"ix":4},"sa":{"a":0,"k":0,"ix":5},"nm":"변형"}],"nm":"그룹 1","np":4,"cix":2,"bm":0,"ix":1,"mn":"ADBE Vector Group","hd":false},{"ty":"gr","it":[{"ind":0,"ty":"sh","ix":1,"ks":{"a":0,"k":{"i":[[-2.175,0],[0,-2.175],[2.175,0],[0,2.176]],"o":[[2.175,0],[0,2.176],[-2.175,0],[0,-2.175]],"v":[[0,-3.939],[3.939,0],[0,3.939],[-3.939,0]],"c":true},"ix":2},"nm":"패스 1","mn":"ADBE Vector Shape - Group","hd":false},{"ty":"fl","c":{"a":0,"k":[1,1,1,1],"ix":4},"o":{"a":0,"k":100,"ix":5},"r":1,"bm":0,"nm":"칠 1","mn":"ADBE Vector Graphic - Fill","hd":false},{"ty":"tr","p":{"a":0,"k":[884.599,1147.435],"ix":2},"a":{"a":0,"k":[0,0],"ix":1},"s":{"a":0,"k":[100,100],"ix":3},"r":{"a":0,"k":0,"ix":6},"o":{"a":0,"k":100,"ix":7},"sk":{"a":0,"k":0,"ix":4},"sa":{"a":0,"k":0,"ix":5},"nm":"변형"}],"nm":"그룹 2","np":4,"cix":2,"bm":0,"ix":2,"mn":"ADBE Vector Group","hd":false},{"ty":"gr","it":[{"ind":0,"ty":"sh","ix":1,"ks":{"a":0,"k":{"i":[[-2.175,0],[0,-2.175],[2.175,0],[0,2.176]],"o":[[2.175,0],[0,2.176],[-2.175,0],[0,-2.175]],"v":[[0,-3.938],[3.939,0.001],[0,3.94],[-3.939,0.001]],"c":true},"ix":2},"nm":"패스 1","mn":"ADBE Vector Shape - Group","hd":false},{"ty":"fl","c":{"a":0,"k":[1,1,1,1],"ix":4},"o":{"a":0,"k":100,"ix":5},"r":1,"bm":0,"nm":"칠 1","mn":"ADBE Vector Graphic - Fill","hd":false},{"ty":"tr","p":{"a":0,"k":[354.142,680.002],"ix":2},"a":{"a":0,"k":[0,0],"ix":1},"s":{"a":0,"k":[100,100],"ix":3},"r":{"a":0,"k":0,"ix":6},"o":{"a":0,"k":100,"ix":7},"sk":{"a":0,"k":0,"ix":4},"sa":{"a":0,"k":0,"ix":5},"nm":"변형"}],"nm":"그룹 3","np":4,"cix":2,"bm":0,"ix":3,"mn":"ADBE Vector Group","hd":false},{"ty":"gr","it":[{"ind":0,"ty":"sh","ix":1,"ks":{"a":0,"k":{"i":[[-2.175,0],[0,-2.175],[2.175,0],[0,2.176]],"o":[[2.175,0],[0,2.176],[-2.175,0],[0,-2.175]],"v":[[0,-3.938],[3.939,0.001],[0,3.94],[-3.939,0.001]],"c":true},"ix":2},"nm":"패스 1","mn":"ADBE Vector Shape - Group","hd":false},{"ty":"fl","c":{"a":0,"k":[1,1,1,1],"ix":4},"o":{"a":0,"k":100,"ix":5},"r":1,"bm":0,"nm":"칠 1","mn":"ADBE Vector Graphic - Fill","hd":false},{"ty":"tr","p":{"a":0,"k":[913.486,580.212],"ix":2},"a":{"a":0,"k":[0,0],"ix":1},"s":{"a":0,"k":[100,100],"ix":3},"r":{"a":0,"k":0,"ix":6},"o":{"a":0,"k":100,"ix":7},"sk":{"a":0,"k":0,"ix":4},"sa":{"a":0,"k":0,"ix":5},"nm":"변형"}],"nm":"그룹 4","np":4,"cix":2,"bm":0,"ix":4,"mn":"ADBE Vector Group","hd":false},{"ty":"gr","it":[{"ind":0,"ty":"sh","ix":1,"ks":{"a":0,"k":{"i":[[-1.45,0],[0,-1.45],[1.45,0],[0,1.45]],"o":[[1.45,0],[0,1.45],[-1.45,0],[0,-1.45]],"v":[[0,-2.626],[2.626,0],[0,2.626],[-2.626,0]],"c":true},"ix":2},"nm":"패스 1","mn":"ADBE Vector Shape - Group","hd":false},{"ty":"fl","c":{"a":0,"k":[1,1,1,1],"ix":4},"o":{"a":0,"k":100,"ix":5},"r":1,"bm":0,"nm":"칠 1","mn":"ADBE Vector Graphic - Fill","hd":false},{"ty":"tr","p":{"a":0,"k":[103.357,922.91],"ix":2},"a":{"a":0,"k":[0,0],"ix":1},"s":{"a":0,"k":[100,100],"ix":3},"r":{"a":0,"k":0,"ix":6},"o":{"a":0,"k":100,"ix":7},"sk":{"a":0,"k":0,"ix":4},"sa":{"a":0,"k":0,"ix":5},"nm":"변형"}],"nm":"그룹 5","np":4,"cix":2,"bm":0,"ix":5,"mn":"ADBE Vector Group","hd":false},{"ty":"gr","it":[{"ind":0,"ty":"sh","ix":1,"ks":{"a":0,"k":{"i":[[-1.45,0],[0,-1.45],[1.45,0],[0,1.45]],"o":[[1.45,0],[0,1.45],[-1.45,0],[0,-1.45]],"v":[[0,-2.626],[2.626,0],[0,2.626],[-2.626,0]],"c":true},"ix":2},"nm":"패스 1","mn":"ADBE Vector Shape - Group","hd":false},{"ty":"fl","c":{"a":0,"k":[1,1,1,1],"ix":4},"o":{"a":0,"k":100,"ix":5},"r":1,"bm":0,"nm":"칠 1","mn":"ADBE Vector Graphic - Fill","hd":false},{"ty":"tr","p":{"a":0,"k":[77.097,1587.294],"ix":2},"a":{"a":0,"k":[0,0],"ix":1},"s":{"a":0,"k":[100,100],"ix":3},"r":{"a":0,"k":0,"ix":6},"o":{"a":0,"k":100,"ix":7},"sk":{"a":0,"k":0,"ix":4},"sa":{"a":0,"k":0,"ix":5},"nm":"변형"}],"nm":"그룹 6","np":4,"cix":2,"bm":0,"ix":6,"mn":"ADBE Vector Group","hd":false},{"ty":"gr","it":[{"ind":0,"ty":"sh","ix":1,"ks":{"a":0,"k":{"i":[[-1.45,0],[0,-1.45],[1.45,0],[0,1.45]],"o":[[1.45,0],[0,1.45],[-1.45,0],[0,-1.45]],"v":[[0,-2.626],[2.626,0],[0,2.626],[-2.626,0]],"c":true},"ix":2},"nm":"패스 1","mn":"ADBE Vector Shape - Group","hd":false},{"ty":"fl","c":{"a":0,"k":[1,1,1,1],"ix":4},"o":{"a":0,"k":100,"ix":5},"r":1,"bm":0,"nm":"칠 1","mn":"ADBE Vector Graphic - Fill","hd":false},{"ty":"tr","p":{"a":0,"k":[612.806,1836.766],"ix":2},"a":{"a":0,"k":[0,0],"ix":1},"s":{"a":0,"k":[100,100],"ix":3},"r":{"a":0,"k":0,"ix":6},"o":{"a":0,"k":100,"ix":7},"sk":{"a":0,"k":0,"ix":4},"sa":{"a":0,"k":0,"ix":5},"nm":"변형"}],"nm":"그룹 7","np":4,"cix":2,"bm":0,"ix":7,"mn":"ADBE Vector Group","hd":false},{"ty":"gr","it":[{"ind":0,"ty":"sh","ix":1,"ks":{"a":0,"k":{"i":[[-1.45,0],[0,-1.45],[1.45,0],[0,1.45]],"o":[[1.45,0],[0,1.45],[-1.45,0],[0,-1.45]],"v":[[0.002,-2.627],[2.628,-0.001],[0.002,2.625],[-2.624,-0.001]],"c":true},"ix":2},"nm":"패스 1","mn":"ADBE Vector Shape - Group","hd":false},{"ty":"fl","c":{"a":0,"k":[1,1,1,1],"ix":4},"o":{"a":0,"k":100,"ix":5},"r":1,"bm":0,"nm":"칠 1","mn":"ADBE Vector Graphic - Fill","hd":false},{"ty":"tr","p":{"a":0,"k":[1053.976,1290.555],"ix":2},"a":{"a":0,"k":[0,0],"ix":1},"s":{"a":0,"k":[100,100],"ix":3},"r":{"a":0,"k":0,"ix":6},"o":{"a":0,"k":100,"ix":7},"sk":{"a":0,"k":0,"ix":4},"sa":{"a":0,"k":0,"ix":5},"nm":"변형"}],"nm":"그룹 8","np":4,"cix":2,"bm":0,"ix":8,"mn":"ADBE Vector Group","hd":false},{"ty":"gr","it":[{"ind":0,"ty":"sh","ix":1,"ks":{"a":0,"k":{"i":[[-1.45,0],[0,-1.45],[1.45,0],[0,1.45]],"o":[[1.45,0],[0,1.45],[-1.45,0],[0,-1.45]],"v":[[0,-2.628],[2.626,-0.002],[0,2.624],[-2.626,-0.002]],"c":true},"ix":2},"nm":"패스 1","mn":"ADBE Vector Shape - Group","hd":false},{"ty":"fl","c":{"a":0,"k":[1,1,1,1],"ix":4},"o":{"a":0,"k":100,"ix":5},"r":1,"bm":0,"nm":"칠 1","mn":"ADBE Vector Graphic - Fill","hd":false},{"ty":"tr","p":{"a":0,"k":[169.008,1364.084],"ix":2},"a":{"a":0,"k":[0,0],"ix":1},"s":{"a":0,"k":[100,100],"ix":3},"r":{"a":0,"k":0,"ix":6},"o":{"a":0,"k":100,"ix":7},"sk":{"a":0,"k":0,"ix":4},"sa":{"a":0,"k":0,"ix":5},"nm":"변형"}],"nm":"그룹 9","np":4,"cix":2,"bm":0,"ix":9,"mn":"ADBE Vector Group","hd":false},{"ty":"gr","it":[{"ind":0,"ty":"sh","ix":1,"ks":{"a":0,"k":{"i":[[-1.45,0],[0,-1.45],[1.45,0],[0,1.45]],"o":[[1.45,0],[0,1.45],[-1.45,0],[0,-1.45]],"v":[[0,-2.626],[2.626,0],[0,2.626],[-2.626,0]],"c":true},"ix":2},"nm":"패스 1","mn":"ADBE Vector Shape - Group","hd":false},{"ty":"fl","c":{"a":0,"k":[1,1,1,1],"ix":4},"o":{"a":0,"k":100,"ix":5},"r":1,"bm":0,"nm":"칠 1","mn":"ADBE Vector Graphic - Fill","hd":false},{"ty":"tr","p":{"a":0,"k":[646.944,1424.48],"ix":2},"a":{"a":0,"k":[0,0],"ix":1},"s":{"a":0,"k":[100,100],"ix":3},"r":{"a":0,"k":0,"ix":6},"o":{"a":0,"k":100,"ix":7},"sk":{"a":0,"k":0,"ix":4},"sa":{"a":0,"k":0,"ix":5},"nm":"변형"}],"nm":"그룹 10","np":4,"cix":2,"bm":0,"ix":10,"mn":"ADBE Vector Group","hd":false},{"ty":"gr","it":[{"ind":0,"ty":"sh","ix":1,"ks":{"a":0,"k":{"i":[[-1.45,0],[0,-1.45],[1.45,0],[0,1.45]],"o":[[1.45,0],[0,1.45],[-1.45,0],[0,-1.45]],"v":[[0,-2.625],[2.626,0.001],[0,2.627],[-2.626,0.001]],"c":true},"ix":2},"nm":"패스 1","mn":"ADBE Vector Shape - Group","hd":false},{"ty":"fl","c":{"a":0,"k":[1,1,1,1],"ix":4},"o":{"a":0,"k":100,"ix":5},"r":1,"bm":0,"nm":"칠 1","mn":"ADBE Vector Graphic - Fill","hd":false},{"ty":"tr","p":{"a":0,"k":[909.547,938.665],"ix":2},"a":{"a":0,"k":[0,0],"ix":1},"s":{"a":0,"k":[100,100],"ix":3},"r":{"a":0,"k":0,"ix":6},"o":{"a":0,"k":100,"ix":7},"sk":{"a":0,"k":0,"ix":4},"sa":{"a":0,"k":0,"ix":5},"nm":"변형"}],"nm":"그룹 11","np":4,"cix":2,"bm":0,"ix":11,"mn":"ADBE Vector Group","hd":false},{"ty":"gr","it":[{"ind":0,"ty":"sh","ix":1,"ks":{"a":0,"k":{"i":[[-1.45,0],[0,-1.45],[1.45,0],[0,1.45]],"o":[[1.45,0],[0,1.45],[-1.45,0],[0,-1.45]],"v":[[0,-2.624],[2.626,0.002],[0,2.628],[-2.626,0.002]],"c":true},"ix":2},"nm":"패스 1","mn":"ADBE Vector Shape - Group","hd":false},{"ty":"fl","c":{"a":0,"k":[1,1,1,1],"ix":4},"o":{"a":0,"k":100,"ix":5},"r":1,"bm":0,"nm":"칠 1","mn":"ADBE Vector Graphic - Fill","hd":false},{"ty":"tr","p":{"a":0,"k":[846.522,673.436],"ix":2},"a":{"a":0,"k":[0,0],"ix":1},"s":{"a":0,"k":[100,100],"ix":3},"r":{"a":0,"k":0,"ix":6},"o":{"a":0,"k":100,"ix":7},"sk":{"a":0,"k":0,"ix":4},"sa":{"a":0,"k":0,"ix":5},"nm":"변형"}],"nm":"그룹 12","np":4,"cix":2,"bm":0,"ix":12,"mn":"ADBE Vector Group","hd":false},{"ty":"gr","it":[{"ind":0,"ty":"sh","ix":1,"ks":{"a":0,"k":{"i":[[-1.45,0],[0,-1.45],[1.45,0],[0,1.45]],"o":[[1.45,0],[0,1.45],[-1.45,0],[0,-1.45]],"v":[[0,-2.626],[2.626,0],[0,2.626],[-2.626,0]],"c":true},"ix":2},"nm":"패스 1","mn":"ADBE Vector Shape - Group","hd":false},{"ty":"fl","c":{"a":0,"k":[1,1,1,1],"ix":4},"o":{"a":0,"k":100,"ix":5},"r":1,"bm":0,"nm":"칠 1","mn":"ADBE Vector Graphic - Fill","hd":false},{"ty":"tr","p":{"a":0,"k":[452.618,796.86],"ix":2},"a":{"a":0,"k":[0,0],"ix":1},"s":{"a":0,"k":[100,100],"ix":3},"r":{"a":0,"k":0,"ix":6},"o":{"a":0,"k":100,"ix":7},"sk":{"a":0,"k":0,"ix":4},"sa":{"a":0,"k":0,"ix":5},"nm":"변형"}],"nm":"그룹 13","np":4,"cix":2,"bm":0,"ix":13,"mn":"ADBE Vector Group","hd":false},{"ty":"gr","it":[{"ind":0,"ty":"sh","ix":1,"ks":{"a":0,"k":{"i":[[-1.45,0],[0,-1.45],[1.45,0],[0,1.45]],"o":[[1.45,0],[0,1.45],[-1.45,0],[0,-1.45]],"v":[[0,-2.625],[2.626,0.001],[0,2.627],[-2.626,0.001]],"c":true},"ix":2},"nm":"패스 1","mn":"ADBE Vector Shape - Group","hd":false},{"ty":"fl","c":{"a":0,"k":[1,1,1,1],"ix":4},"o":{"a":0,"k":100,"ix":5},"r":1,"bm":0,"nm":"칠 1","mn":"ADBE Vector Graphic - Fill","hd":false},{"ty":"tr","p":{"a":0,"k":[66.593,634.046],"ix":2},"a":{"a":0,"k":[0,0],"ix":1},"s":{"a":0,"k":[100,100],"ix":3},"r":{"a":0,"k":0,"ix":6},"o":{"a":0,"k":100,"ix":7},"sk":{"a":0,"k":0,"ix":4},"sa":{"a":0,"k":0,"ix":5},"nm":"변형"}],"nm":"그룹 14","np":4,"cix":2,"bm":0,"ix":14,"mn":"ADBE Vector Group","hd":false},{"ty":"gr","it":[{"ind":0,"ty":"sh","ix":1,"ks":{"a":0,"k":{"i":[[-0.725,0],[0,-0.725],[0.725,0],[0,0.725]],"o":[[0.725,0],[0,0.725],[-0.725,0],[0,-0.725]],"v":[[0,-1.313],[1.313,0],[0,1.313],[-1.313,0]],"c":true},"ix":2},"nm":"패스 1","mn":"ADBE Vector Shape - Group","hd":false},{"ty":"fl","c":{"a":0,"k":[1,1,1,1],"ix":4},"o":{"a":0,"k":100,"ix":5},"r":1,"bm":0,"nm":"칠 1","mn":"ADBE Vector Graphic - Fill","hd":false},{"ty":"tr","p":{"a":0,"k":[214.963,987.247],"ix":2},"a":{"a":0,"k":[0,0],"ix":1},"s":{"a":0,"k":[100,100],"ix":3},"r":{"a":0,"k":0,"ix":6},"o":{"a":0,"k":100,"ix":7},"sk":{"a":0,"k":0,"ix":4},"sa":{"a":0,"k":0,"ix":5},"nm":"변형"}],"nm":"그룹 15","np":4,"cix":2,"bm":0,"ix":15,"mn":"ADBE Vector Group","hd":false}],"ip":0,"op":90.0000036657751,"st":0,"bm":0},{"ddd":0,"ind":9,"ty":4,"nm":"별1","sr":1,"ks":{"o":{"a":1,"k":[{"i":{"x":[0.833],"y":[0.833]},"o":{"x":[0.167],"y":[0.167]},"t":0,"s":[80]},{"i":{"x":[0.833],"y":[0.833]},"o":{"x":[0.167],"y":[0.167]},"t":75,"s":[30]},{"i":{"x":[0.833],"y":[0.833]},"o":{"x":[0.167],"y":[0.167]},"t":149,"s":[80]},{"i":{"x":[0.833],"y":[0.833]},"o":{"x":[0.167],"y":[0.167]},"t":220,"s":[30]},{"t":294.000011974866,"s":[80]}],"ix":11},"r":{"a":0,"k":0,"ix":10},"p":{"a":0,"k":[562,1218,0],"ix":2},"a":{"a":0,"k":[562.5,1218,0],"ix":1},"s":{"a":0,"k":[100,100,100],"ix":6}},"ao":0,"shapes":[{"ty":"gr","it":[{"ind":0,"ty":"sh","ix":1,"ks":{"a":0,"k":{"i":[[-0.725,0],[0,-0.725],[0.725,0],[0,0.725]],"o":[[0.725,0],[0,0.725],[-0.725,0],[0,-0.725]],"v":[[0,-1.313],[1.313,0],[0,1.313],[-1.313,0]],"c":true},"ix":2},"nm":"패스 1","mn":"ADBE Vector Shape - Group","hd":false},{"ty":"fl","c":{"a":0,"k":[1,1,1,1],"ix":4},"o":{"a":0,"k":100,"ix":5},"r":1,"bm":0,"nm":"칠 1","mn":"ADBE Vector Graphic - Fill","hd":false},{"ty":"tr","p":{"a":0,"k":[1065.795,1034.516],"ix":2},"a":{"a":0,"k":[0,0],"ix":1},"s":{"a":0,"k":[100,100],"ix":3},"r":{"a":0,"k":0,"ix":6},"o":{"a":0,"k":100,"ix":7},"sk":{"a":0,"k":0,"ix":4},"sa":{"a":0,"k":0,"ix":5},"nm":"변형"}],"nm":"그룹 1","np":4,"cix":2,"bm":0,"ix":1,"mn":"ADBE Vector Group","hd":false},{"ty":"gr","it":[{"ind":0,"ty":"sh","ix":1,"ks":{"a":0,"k":{"i":[[-0.725,0],[0,-0.725],[0.725,0],[0,0.725]],"o":[[0.725,0],[0,0.725],[-0.725,0],[0,-0.725]],"v":[[0,-1.313],[1.313,0],[0,1.313],[-1.313,0]],"c":true},"ix":2},"nm":"패스 1","mn":"ADBE Vector Shape - Group","hd":false},{"ty":"fl","c":{"a":0,"k":[1,1,1,1],"ix":4},"o":{"a":0,"k":100,"ix":5},"r":1,"bm":0,"nm":"칠 1","mn":"ADBE Vector Graphic - Fill","hd":false},{"ty":"tr","p":{"a":0,"k":[905.607,1129.053],"ix":2},"a":{"a":0,"k":[0,0],"ix":1},"s":{"a":0,"k":[100,100],"ix":3},"r":{"a":0,"k":0,"ix":6},"o":{"a":0,"k":100,"ix":7},"sk":{"a":0,"k":0,"ix":4},"sa":{"a":0,"k":0,"ix":5},"nm":"변형"}],"nm":"그룹 2","np":4,"cix":2,"bm":0,"ix":2,"mn":"ADBE Vector Group","hd":false},{"ty":"gr","it":[{"ind":0,"ty":"sh","ix":1,"ks":{"a":0,"k":{"i":[[-0.725,0],[0,-0.725],[0.725,0],[0,0.725]],"o":[[0.725,0],[0,0.725],[-0.725,0],[0,-0.725]],"v":[[0,-1.314],[1.313,-0.001],[0,1.312],[-1.313,-0.001]],"c":true},"ix":2},"nm":"패스 1","mn":"ADBE Vector Shape - Group","hd":false},{"ty":"fl","c":{"a":0,"k":[1,1,1,1],"ix":4},"o":{"a":0,"k":100,"ix":5},"r":1,"bm":0,"nm":"칠 1","mn":"ADBE Vector Graphic - Fill","hd":false},{"ty":"tr","p":{"a":0,"k":[432.923,504.06],"ix":2},"a":{"a":0,"k":[0,0],"ix":1},"s":{"a":0,"k":[100,100],"ix":3},"r":{"a":0,"k":0,"ix":6},"o":{"a":0,"k":100,"ix":7},"sk":{"a":0,"k":0,"ix":4},"sa":{"a":0,"k":0,"ix":5},"nm":"변형"}],"nm":"그룹 3","np":4,"cix":2,"bm":0,"ix":3,"mn":"ADBE Vector Group","hd":false},{"ty":"gr","it":[{"ind":0,"ty":"sh","ix":1,"ks":{"a":0,"k":{"i":[[-0.725,0],[0,-0.725],[0.725,0],[0,0.725]],"o":[[0.725,0],[0,0.725],[-0.725,0],[0,-0.725]],"v":[[0,-1.313],[1.313,0],[0,1.313],[-1.313,0]],"c":true},"ix":2},"nm":"패스 1","mn":"ADBE Vector Shape - Group","hd":false},{"ty":"fl","c":{"a":0,"k":[1,1,1,1],"ix":4},"o":{"a":0,"k":100,"ix":5},"r":1,"bm":0,"nm":"칠 1","mn":"ADBE Vector Graphic - Fill","hd":false},{"ty":"tr","p":{"a":0,"k":[1039.535,693.133],"ix":2},"a":{"a":0,"k":[0,0],"ix":1},"s":{"a":0,"k":[100,100],"ix":3},"r":{"a":0,"k":0,"ix":6},"o":{"a":0,"k":100,"ix":7},"sk":{"a":0,"k":0,"ix":4},"sa":{"a":0,"k":0,"ix":5},"nm":"변형"}],"nm":"그룹 4","np":4,"cix":2,"bm":0,"ix":4,"mn":"ADBE Vector Group","hd":false},{"ty":"gr","it":[{"ind":0,"ty":"sh","ix":1,"ks":{"a":0,"k":{"i":[[-0.725,0],[0,-0.725],[0.725,0],[0,0.725]],"o":[[0.725,0],[0,0.725],[-0.725,0],[0,-0.725]],"v":[[0,-1.311],[1.313,0.002],[0,1.315],[-1.313,0.002]],"c":true},"ix":2},"nm":"패스 1","mn":"ADBE Vector Shape - Group","hd":false},{"ty":"fl","c":{"a":0,"k":[1,1,1,1],"ix":4},"o":{"a":0,"k":100,"ix":5},"r":1,"bm":0,"nm":"칠 1","mn":"ADBE Vector Graphic - Fill","hd":false},{"ty":"tr","p":{"a":0,"k":[916.112,792.92],"ix":2},"a":{"a":0,"k":[0,0],"ix":1},"s":{"a":0,"k":[100,100],"ix":3},"r":{"a":0,"k":0,"ix":6},"o":{"a":0,"k":100,"ix":7},"sk":{"a":0,"k":0,"ix":4},"sa":{"a":0,"k":0,"ix":5},"nm":"변형"}],"nm":"그룹 5","np":4,"cix":2,"bm":0,"ix":5,"mn":"ADBE Vector Group","hd":false},{"ty":"gr","it":[{"ind":0,"ty":"sh","ix":1,"ks":{"a":0,"k":{"i":[[-0.725,0],[0,-0.725],[0.725,0],[0,0.725]],"o":[[0.725,0],[0,0.725],[-0.725,0],[0,-0.725]],"v":[[0,-1.313],[1.313,0],[0,1.313],[-1.313,0]],"c":true},"ix":2},"nm":"패스 1","mn":"ADBE Vector Shape - Group","hd":false},{"ty":"fl","c":{"a":0,"k":[1,1,1,1],"ix":4},"o":{"a":0,"k":100,"ix":5},"r":1,"bm":0,"nm":"칠 1","mn":"ADBE Vector Graphic - Fill","hd":false},{"ty":"tr","p":{"a":0,"k":[262.231,664.246],"ix":2},"a":{"a":0,"k":[0,0],"ix":1},"s":{"a":0,"k":[100,100],"ix":3},"r":{"a":0,"k":0,"ix":6},"o":{"a":0,"k":100,"ix":7},"sk":{"a":0,"k":0,"ix":4},"sa":{"a":0,"k":0,"ix":5},"nm":"변형"}],"nm":"그룹 6","np":4,"cix":2,"bm":0,"ix":6,"mn":"ADBE Vector Group","hd":false},{"ty":"gr","it":[{"ind":0,"ty":"sh","ix":1,"ks":{"a":0,"k":{"i":[[-0.725,0],[0,-0.725],[0.725,0],[0,0.725]],"o":[[0.725,0],[0,0.725],[-0.725,0],[0,-0.725]],"v":[[0,-1.313],[1.313,0],[0,1.313],[-1.313,0]],"c":true},"ix":2},"nm":"패스 1","mn":"ADBE Vector Shape - Group","hd":false},{"ty":"fl","c":{"a":0,"k":[1,1,1,1],"ix":4},"o":{"a":0,"k":100,"ix":5},"r":1,"bm":0,"nm":"칠 1","mn":"ADBE Vector Graphic - Fill","hd":false},{"ty":"tr","p":{"a":0,"k":[235.971,630.107],"ix":2},"a":{"a":0,"k":[0,0],"ix":1},"s":{"a":0,"k":[100,100],"ix":3},"r":{"a":0,"k":0,"ix":6},"o":{"a":0,"k":100,"ix":7},"sk":{"a":0,"k":0,"ix":4},"sa":{"a":0,"k":0,"ix":5},"nm":"변형"}],"nm":"그룹 7","np":4,"cix":2,"bm":0,"ix":7,"mn":"ADBE Vector Group","hd":false},{"ty":"gr","it":[{"ind":0,"ty":"sh","ix":1,"ks":{"a":0,"k":{"i":[[-1.45,0],[0,-1.45],[1.45,0],[0,1.45]],"o":[[1.45,0],[0,1.45],[-1.45,0],[0,-1.45]],"v":[[0,-2.626],[2.626,0],[0,2.626],[-2.626,0]],"c":true},"ix":2},"nm":"패스 1","mn":"ADBE Vector Shape - Group","hd":false},{"ty":"fl","c":{"a":0,"k":[1,1,1,1],"ix":4},"o":{"a":0,"k":100,"ix":5},"r":1,"bm":0,"nm":"칠 1","mn":"ADBE Vector Graphic - Fill","hd":false},{"ty":"tr","p":{"a":0,"k":[780.871,1834.14],"ix":2},"a":{"a":0,"k":[0,0],"ix":1},"s":{"a":0,"k":[100,100],"ix":3},"r":{"a":0,"k":0,"ix":6},"o":{"a":0,"k":100,"ix":7},"sk":{"a":0,"k":0,"ix":4},"sa":{"a":0,"k":0,"ix":5},"nm":"변형"}],"nm":"그룹 8","np":4,"cix":2,"bm":0,"ix":8,"mn":"ADBE Vector Group","hd":false},{"ty":"gr","it":[{"ind":0,"ty":"sh","ix":1,"ks":{"a":0,"k":{"i":[[-1.45,0],[0,-1.45],[1.45,0],[0,1.45]],"o":[[1.45,0],[0,1.45],[-1.45,0],[0,-1.45]],"v":[[0,-2.626],[2.626,0],[0,2.626],[-2.626,0]],"c":true},"ix":2},"nm":"패스 1","mn":"ADBE Vector Shape - Group","hd":false},{"ty":"fl","c":{"a":0,"k":[1,1,1,1],"ix":4},"o":{"a":0,"k":100,"ix":5},"r":1,"bm":0,"nm":"칠 1","mn":"ADBE Vector Graphic - Fill","hd":false},{"ty":"tr","p":{"a":0,"k":[56.089,1642.44],"ix":2},"a":{"a":0,"k":[0,0],"ix":1},"s":{"a":0,"k":[100,100],"ix":3},"r":{"a":0,"k":0,"ix":6},"o":{"a":0,"k":100,"ix":7},"sk":{"a":0,"k":0,"ix":4},"sa":{"a":0,"k":0,"ix":5},"nm":"변형"}],"nm":"그룹 9","np":4,"cix":2,"bm":0,"ix":9,"mn":"ADBE Vector Group","hd":false},{"ty":"gr","it":[{"ind":0,"ty":"sh","ix":1,"ks":{"a":0,"k":{"i":[[-1.45,0],[0,-1.45],[1.45,0],[0,1.45]],"o":[[1.45,0],[0,1.45],[-1.45,0],[0,-1.45]],"v":[[0,-2.626],[2.626,0],[0,2.626],[-2.626,0]],"c":true},"ix":2},"nm":"패스 1","mn":"ADBE Vector Shape - Group","hd":false},{"ty":"fl","c":{"a":0,"k":[1,1,1,1],"ix":4},"o":{"a":0,"k":100,"ix":5},"r":1,"bm":0,"nm":"칠 1","mn":"ADBE Vector Graphic - Fill","hd":false},{"ty":"tr","p":{"a":0,"k":[368.585,1910.295],"ix":2},"a":{"a":0,"k":[0,0],"ix":1},"s":{"a":0,"k":[100,100],"ix":3},"r":{"a":0,"k":0,"ix":6},"o":{"a":0,"k":100,"ix":7},"sk":{"a":0,"k":0,"ix":4},"sa":{"a":0,"k":0,"ix":5},"nm":"변형"}],"nm":"그룹 10","np":4,"cix":2,"bm":0,"ix":10,"mn":"ADBE Vector Group","hd":false}],"ip":0,"op":90.0000036657751,"st":0,"bm":0}],"markers":[]}